{"name": "bin\\Win\\Atlases\\Surface_LavaFallA20", "version": 4, "subAtlases": [{"name": "Fx\\LavaFallA\\LavaFallA0001", "rect": {"x": 1, "y": 1, "width": 69, "height": 501}, "topLeft": {"x": 30, "y": 25}, "originalSize": {"x": 128, "y": 540}, "scaleRatio": {"x": 1.0, "y": 1.0}, "isMulti": false, "isMip": false, "isAlpha8": false, "hull": []}, {"name": "Fx\\LavaFallA\\LavaFallA0021", "rect": {"x": 1, "y": 504, "width": 68, "height": 501}, "topLeft": {"x": 30, "y": 25}, "originalSize": {"x": 128, "y": 540}, "scaleRatio": {"x": 1.0, "y": 1.0}, "isMulti": false, "isMip": false, "isAlpha8": false, "hull": []}, {"name": "Fx\\LavaFallA\\LavaFallA0002", "rect": {"x": 1, "y": 1007, "width": 69, "height": 501}, "topLeft": {"x": 30, "y": 25}, "originalSize": {"x": 128, "y": 540}, "scaleRatio": {"x": 1.0, "y": 1.0}, "isMulti": false, "isMip": false, "isAlpha8": false, "hull": []}, {"name": "Fx\\LavaFallA\\LavaFallA0003", "rect": {"x": 71, "y": 504, "width": 69, "height": 501}, "topLeft": {"x": 30, "y": 25}, "originalSize": {"x": 128, "y": 540}, "scaleRatio": {"x": 1.0, "y": 1.0}, "isMulti": false, "isMip": false, "isAlpha8": false, "hull": []}, {"name": "Fx\\LavaFallA\\LavaFallA0004", "rect": {"x": 72, "y": 1, "width": 69, "height": 501}, "topLeft": {"x": 30, "y": 25}, "originalSize": {"x": 128, "y": 540}, "scaleRatio": {"x": 1.0, "y": 1.0}, "isMulti": false, "isMip": false, "isAlpha8": false, "hull": []}, {"name": "Fx\\LavaFallA\\LavaFallA0005", "rect": {"x": 1, "y": 1510, "width": 69, "height": 501}, "topLeft": {"x": 30, "y": 25}, "originalSize": {"x": 128, "y": 540}, "scaleRatio": {"x": 1.0, "y": 1.0}, "isMulti": false, "isMip": false, "isAlpha8": false, "hull": []}, {"name": "Fx\\LavaFallA\\LavaFallA0006", "rect": {"x": 72, "y": 1007, "width": 69, "height": 501}, "topLeft": {"x": 30, "y": 25}, "originalSize": {"x": 128, "y": 540}, "scaleRatio": {"x": 1.0, "y": 1.0}, "isMulti": false, "isMip": false, "isAlpha8": false, "hull": []}, {"name": "Fx\\LavaFallA\\LavaFallA0007", "rect": {"x": 142, "y": 504, "width": 69, "height": 501}, "topLeft": {"x": 30, "y": 25}, "originalSize": {"x": 128, "y": 540}, "scaleRatio": {"x": 1.0, "y": 1.0}, "isMulti": false, "isMip": false, "isAlpha8": false, "hull": []}, {"name": "Fx\\LavaFallA\\LavaFallA0008", "rect": {"x": 143, "y": 1, "width": 69, "height": 501}, "topLeft": {"x": 30, "y": 25}, "originalSize": {"x": 128, "y": 540}, "scaleRatio": {"x": 1.0, "y": 1.0}, "isMulti": false, "isMip": false, "isAlpha8": false, "hull": []}, {"name": "Fx\\LavaFallA\\LavaFallA0009", "rect": {"x": 72, "y": 1510, "width": 69, "height": 501}, "topLeft": {"x": 30, "y": 25}, "originalSize": {"x": 128, "y": 540}, "scaleRatio": {"x": 1.0, "y": 1.0}, "isMulti": false, "isMip": false, "isAlpha8": false, "hull": []}, {"name": "Fx\\LavaFallA\\LavaFallA0010", "rect": {"x": 143, "y": 1007, "width": 69, "height": 501}, "topLeft": {"x": 30, "y": 25}, "originalSize": {"x": 128, "y": 540}, "scaleRatio": {"x": 1.0, "y": 1.0}, "isMulti": false, "isMip": false, "isAlpha8": false, "hull": []}, {"name": "Fx\\LavaFallA\\LavaFallA0011", "rect": {"x": 213, "y": 504, "width": 69, "height": 501}, "topLeft": {"x": 30, "y": 25}, "originalSize": {"x": 128, "y": 540}, "scaleRatio": {"x": 1.0, "y": 1.0}, "isMulti": false, "isMip": false, "isAlpha8": false, "hull": []}, {"name": "Fx\\LavaFallA\\LavaFallA0012", "rect": {"x": 214, "y": 1, "width": 69, "height": 501}, "topLeft": {"x": 30, "y": 25}, "originalSize": {"x": 128, "y": 540}, "scaleRatio": {"x": 1.0, "y": 1.0}, "isMulti": false, "isMip": false, "isAlpha8": false, "hull": []}, {"name": "Fx\\LavaFallA\\LavaFallA0022", "rect": {"x": 143, "y": 1510, "width": 68, "height": 501}, "topLeft": {"x": 30, "y": 25}, "originalSize": {"x": 128, "y": 540}, "scaleRatio": {"x": 1.0, "y": 1.0}, "isMulti": false, "isMip": false, "isAlpha8": false, "hull": []}, {"name": "Fx\\LavaFallA\\LavaFallA0013", "rect": {"x": 213, "y": 1510, "width": 69, "height": 501}, "topLeft": {"x": 30, "y": 25}, "originalSize": {"x": 128, "y": 540}, "scaleRatio": {"x": 1.0, "y": 1.0}, "isMulti": false, "isMip": false, "isAlpha8": false, "hull": []}, {"name": "Fx\\LavaFallA\\LavaFallA0014", "rect": {"x": 214, "y": 1007, "width": 69, "height": 501}, "topLeft": {"x": 30, "y": 25}, "originalSize": {"x": 128, "y": 540}, "scaleRatio": {"x": 1.0, "y": 1.0}, "isMulti": false, "isMip": false, "isAlpha8": false, "hull": []}, {"name": "Fx\\LavaFallA\\LavaFallA0015", "rect": {"x": 284, "y": 504, "width": 69, "height": 501}, "topLeft": {"x": 30, "y": 25}, "originalSize": {"x": 128, "y": 540}, "scaleRatio": {"x": 1.0, "y": 1.0}, "isMulti": false, "isMip": false, "isAlpha8": false, "hull": []}, {"name": "Fx\\LavaFallA\\LavaFallA0016", "rect": {"x": 285, "y": 1, "width": 69, "height": 501}, "topLeft": {"x": 30, "y": 25}, "originalSize": {"x": 128, "y": 540}, "scaleRatio": {"x": 1.0, "y": 1.0}, "isMulti": false, "isMip": false, "isAlpha8": false, "hull": []}, {"name": "Fx\\LavaFallA\\LavaFallA0017", "rect": {"x": 284, "y": 1510, "width": 69, "height": 501}, "topLeft": {"x": 30, "y": 25}, "originalSize": {"x": 128, "y": 540}, "scaleRatio": {"x": 1.0, "y": 1.0}, "isMulti": false, "isMip": false, "isAlpha8": false, "hull": []}, {"name": "Fx\\LavaFallA\\LavaFallA0018", "rect": {"x": 285, "y": 1007, "width": 69, "height": 501}, "topLeft": {"x": 30, "y": 25}, "originalSize": {"x": 128, "y": 540}, "scaleRatio": {"x": 1.0, "y": 1.0}, "isMulti": false, "isMip": false, "isAlpha8": false, "hull": []}, {"name": "Fx\\LavaFallA\\LavaFallA0019", "rect": {"x": 355, "y": 504, "width": 69, "height": 501}, "topLeft": {"x": 30, "y": 25}, "originalSize": {"x": 128, "y": 540}, "scaleRatio": {"x": 1.0, "y": 1.0}, "isMulti": false, "isMip": false, "isAlpha8": false, "hull": []}, {"name": "Fx\\LavaFallA\\LavaFallA0020", "rect": {"x": 356, "y": 1, "width": 69, "height": 501}, "topLeft": {"x": 30, "y": 25}, "originalSize": {"x": 128, "y": 540}, "scaleRatio": {"x": 1.0, "y": 1.0}, "isMulti": false, "isMip": false, "isAlpha8": false, "hull": []}, {"name": "Fx\\LavaFallA\\LavaFallA0098", "rect": {"x": 355, "y": 1510, "width": 69, "height": 501}, "topLeft": {"x": 30, "y": 25}, "originalSize": {"x": 128, "y": 540}, "scaleRatio": {"x": 1.0, "y": 1.0}, "isMulti": false, "isMip": false, "isAlpha8": false, "hull": []}, {"name": "Fx\\LavaFallA\\LavaFallA0099", "rect": {"x": 356, "y": 1007, "width": 69, "height": 501}, "topLeft": {"x": 30, "y": 25}, "originalSize": {"x": 128, "y": 540}, "scaleRatio": {"x": 1.0, "y": 1.0}, "isMulti": false, "isMip": false, "isAlpha8": false, "hull": []}, {"name": "Fx\\LavaFallA\\LavaFallA0100", "rect": {"x": 426, "y": 504, "width": 69, "height": 501}, "topLeft": {"x": 30, "y": 25}, "originalSize": {"x": 128, "y": 540}, "scaleRatio": {"x": 1.0, "y": 1.0}, "isMulti": false, "isMip": false, "isAlpha8": false, "hull": []}, {"name": "Fx\\LavaFallA\\LavaFallA0023", "rect": {"x": 427, "y": 1, "width": 68, "height": 501}, "topLeft": {"x": 30, "y": 25}, "originalSize": {"x": 128, "y": 540}, "scaleRatio": {"x": 1.0, "y": 1.0}, "isMulti": false, "isMip": false, "isAlpha8": false, "hull": []}, {"name": "Fx\\LavaFallA\\LavaFallA0024", "rect": {"x": 426, "y": 1510, "width": 68, "height": 501}, "topLeft": {"x": 30, "y": 25}, "originalSize": {"x": 128, "y": 540}, "scaleRatio": {"x": 1.0, "y": 1.0}, "isMulti": false, "isMip": false, "isAlpha8": false, "hull": []}, {"name": "Fx\\LavaFallA\\LavaFallA0025", "rect": {"x": 427, "y": 1007, "width": 68, "height": 501}, "topLeft": {"x": 30, "y": 25}, "originalSize": {"x": 128, "y": 540}, "scaleRatio": {"x": 1.0, "y": 1.0}, "isMulti": false, "isMip": false, "isAlpha8": false, "hull": []}, {"name": "Fx\\LavaFallA\\LavaFallA0026", "rect": {"x": 496, "y": 1510, "width": 68, "height": 501}, "topLeft": {"x": 30, "y": 25}, "originalSize": {"x": 128, "y": 540}, "scaleRatio": {"x": 1.0, "y": 1.0}, "isMulti": false, "isMip": false, "isAlpha8": false, "hull": []}, {"name": "Fx\\LavaFallA\\LavaFallA0027", "rect": {"x": 497, "y": 1, "width": 68, "height": 501}, "topLeft": {"x": 30, "y": 25}, "originalSize": {"x": 128, "y": 540}, "scaleRatio": {"x": 1.0, "y": 1.0}, "isMulti": false, "isMip": false, "isAlpha8": false, "hull": []}, {"name": "Fx\\LavaFallA\\LavaFallA0028", "rect": {"x": 497, "y": 504, "width": 68, "height": 501}, "topLeft": {"x": 30, "y": 25}, "originalSize": {"x": 128, "y": 540}, "scaleRatio": {"x": 1.0, "y": 1.0}, "isMulti": false, "isMip": false, "isAlpha8": false, "hull": []}, {"name": "Fx\\LavaFallA\\LavaFallA0029", "rect": {"x": 497, "y": 1007, "width": 68, "height": 501}, "topLeft": {"x": 30, "y": 25}, "originalSize": {"x": 128, "y": 540}, "scaleRatio": {"x": 1.0, "y": 1.0}, "isMulti": false, "isMip": false, "isAlpha8": false, "hull": []}, {"name": "Fx\\LavaFallA\\LavaFallA0030", "rect": {"x": 566, "y": 1510, "width": 68, "height": 501}, "topLeft": {"x": 30, "y": 25}, "originalSize": {"x": 128, "y": 540}, "scaleRatio": {"x": 1.0, "y": 1.0}, "isMulti": false, "isMip": false, "isAlpha8": false, "hull": [{"x": 35, "y": 242}, {"x": 12, "y": 251}, {"x": -8, "y": 251}, {"x": -35, "y": 239}, {"x": -35, "y": -251}, {"x": 35, "y": -251}]}, {"name": "Fx\\LavaFallA\\LavaFallA0031", "rect": {"x": 567, "y": 1, "width": 68, "height": 501}, "topLeft": {"x": 30, "y": 25}, "originalSize": {"x": 128, "y": 540}, "scaleRatio": {"x": 1.0, "y": 1.0}, "isMulti": false, "isMip": false, "isAlpha8": false, "hull": [{"x": 35, "y": 242}, {"x": 12, "y": 251}, {"x": -8, "y": 251}, {"x": -35, "y": 239}, {"x": -35, "y": -251}, {"x": 35, "y": -251}]}, {"name": "Fx\\LavaFallA\\LavaFallA0032", "rect": {"x": 567, "y": 504, "width": 68, "height": 501}, "topLeft": {"x": 30, "y": 25}, "originalSize": {"x": 128, "y": 540}, "scaleRatio": {"x": 1.0, "y": 1.0}, "isMulti": false, "isMip": false, "isAlpha8": false, "hull": [{"x": 35, "y": 242}, {"x": 12, "y": 251}, {"x": -8, "y": 251}, {"x": -35, "y": 239}, {"x": -35, "y": -251}, {"x": 35, "y": -251}]}, {"name": "Fx\\LavaFallA\\LavaFallA0033", "rect": {"x": 567, "y": 1007, "width": 68, "height": 501}, "topLeft": {"x": 30, "y": 25}, "originalSize": {"x": 128, "y": 540}, "scaleRatio": {"x": 1.0, "y": 1.0}, "isMulti": false, "isMip": false, "isAlpha8": false, "hull": []}, {"name": "Fx\\LavaFallA\\LavaFallA0034", "rect": {"x": 636, "y": 1510, "width": 68, "height": 501}, "topLeft": {"x": 30, "y": 25}, "originalSize": {"x": 128, "y": 540}, "scaleRatio": {"x": 1.0, "y": 1.0}, "isMulti": false, "isMip": false, "isAlpha8": false, "hull": []}, {"name": "Fx\\LavaFallA\\LavaFallA0035", "rect": {"x": 637, "y": 1, "width": 68, "height": 501}, "topLeft": {"x": 30, "y": 25}, "originalSize": {"x": 128, "y": 540}, "scaleRatio": {"x": 1.0, "y": 1.0}, "isMulti": false, "isMip": false, "isAlpha8": false, "hull": []}, {"name": "Fx\\LavaFallA\\LavaFallA0036", "rect": {"x": 637, "y": 504, "width": 68, "height": 501}, "topLeft": {"x": 30, "y": 25}, "originalSize": {"x": 128, "y": 540}, "scaleRatio": {"x": 1.0, "y": 1.0}, "isMulti": false, "isMip": false, "isAlpha8": false, "hull": []}, {"name": "Fx\\LavaFallA\\LavaFallA0037", "rect": {"x": 637, "y": 1007, "width": 68, "height": 501}, "topLeft": {"x": 30, "y": 25}, "originalSize": {"x": 128, "y": 540}, "scaleRatio": {"x": 1.0, "y": 1.0}, "isMulti": false, "isMip": false, "isAlpha8": false, "hull": []}, {"name": "Fx\\LavaFallA\\LavaFallA0038", "rect": {"x": 706, "y": 1510, "width": 68, "height": 501}, "topLeft": {"x": 30, "y": 25}, "originalSize": {"x": 128, "y": 540}, "scaleRatio": {"x": 1.0, "y": 1.0}, "isMulti": false, "isMip": false, "isAlpha8": false, "hull": []}, {"name": "Fx\\LavaFallA\\LavaFallA0039", "rect": {"x": 707, "y": 1, "width": 68, "height": 501}, "topLeft": {"x": 30, "y": 25}, "originalSize": {"x": 128, "y": 540}, "scaleRatio": {"x": 1.0, "y": 1.0}, "isMulti": false, "isMip": false, "isAlpha8": false, "hull": [{"x": 35, "y": 243}, {"x": 11, "y": 251}, {"x": -9, "y": 251}, {"x": -35, "y": 238}, {"x": -35, "y": -251}, {"x": 35, "y": -251}]}, {"name": "Fx\\LavaFallA\\LavaFallA0040", "rect": {"x": 707, "y": 504, "width": 68, "height": 501}, "topLeft": {"x": 30, "y": 25}, "originalSize": {"x": 128, "y": 540}, "scaleRatio": {"x": 1.0, "y": 1.0}, "isMulti": false, "isMip": false, "isAlpha8": false, "hull": []}, {"name": "Fx\\LavaFallA\\LavaFallA0041", "rect": {"x": 707, "y": 1007, "width": 68, "height": 501}, "topLeft": {"x": 30, "y": 25}, "originalSize": {"x": 128, "y": 540}, "scaleRatio": {"x": 1.0, "y": 1.0}, "isMulti": false, "isMip": false, "isAlpha8": false, "hull": []}, {"name": "Fx\\LavaFallA\\LavaFallA0042", "rect": {"x": 776, "y": 1510, "width": 68, "height": 501}, "topLeft": {"x": 30, "y": 25}, "originalSize": {"x": 128, "y": 540}, "scaleRatio": {"x": 1.0, "y": 1.0}, "isMulti": false, "isMip": false, "isAlpha8": false, "hull": []}, {"name": "Fx\\LavaFallA\\LavaFallA0043", "rect": {"x": 777, "y": 1, "width": 68, "height": 501}, "topLeft": {"x": 30, "y": 25}, "originalSize": {"x": 128, "y": 540}, "scaleRatio": {"x": 1.0, "y": 1.0}, "isMulti": false, "isMip": false, "isAlpha8": false, "hull": []}, {"name": "Fx\\LavaFallA\\LavaFallA0044", "rect": {"x": 777, "y": 504, "width": 68, "height": 501}, "topLeft": {"x": 30, "y": 25}, "originalSize": {"x": 128, "y": 540}, "scaleRatio": {"x": 1.0, "y": 1.0}, "isMulti": false, "isMip": false, "isAlpha8": false, "hull": []}, {"name": "Fx\\LavaFallA\\LavaFallA0045", "rect": {"x": 777, "y": 1007, "width": 68, "height": 501}, "topLeft": {"x": 30, "y": 25}, "originalSize": {"x": 128, "y": 540}, "scaleRatio": {"x": 1.0, "y": 1.0}, "isMulti": false, "isMip": false, "isAlpha8": false, "hull": []}, {"name": "Fx\\LavaFallA\\LavaFallA0046", "rect": {"x": 846, "y": 1510, "width": 68, "height": 501}, "topLeft": {"x": 30, "y": 25}, "originalSize": {"x": 128, "y": 540}, "scaleRatio": {"x": 1.0, "y": 1.0}, "isMulti": false, "isMip": false, "isAlpha8": false, "hull": []}, {"name": "Fx\\LavaFallA\\LavaFallA0047", "rect": {"x": 847, "y": 1, "width": 68, "height": 501}, "topLeft": {"x": 30, "y": 25}, "originalSize": {"x": 128, "y": 540}, "scaleRatio": {"x": 1.0, "y": 1.0}, "isMulti": false, "isMip": false, "isAlpha8": false, "hull": []}, {"name": "Fx\\LavaFallA\\LavaFallA0048", "rect": {"x": 847, "y": 504, "width": 68, "height": 501}, "topLeft": {"x": 30, "y": 25}, "originalSize": {"x": 128, "y": 540}, "scaleRatio": {"x": 1.0, "y": 1.0}, "isMulti": false, "isMip": false, "isAlpha8": false, "hull": []}, {"name": "Fx\\LavaFallA\\LavaFallA0049", "rect": {"x": 847, "y": 1007, "width": 68, "height": 501}, "topLeft": {"x": 30, "y": 25}, "originalSize": {"x": 128, "y": 540}, "scaleRatio": {"x": 1.0, "y": 1.0}, "isMulti": false, "isMip": false, "isAlpha8": false, "hull": []}, {"name": "Fx\\LavaFallA\\LavaFallA0050", "rect": {"x": 916, "y": 1510, "width": 68, "height": 501}, "topLeft": {"x": 30, "y": 25}, "originalSize": {"x": 128, "y": 540}, "scaleRatio": {"x": 1.0, "y": 1.0}, "isMulti": false, "isMip": false, "isAlpha8": false, "hull": []}, {"name": "Fx\\LavaFallA\\LavaFallA0051", "rect": {"x": 986, "y": 1, "width": 68, "height": 501}, "topLeft": {"x": 30, "y": 25}, "originalSize": {"x": 128, "y": 540}, "scaleRatio": {"x": 1.0, "y": 1.0}, "isMulti": false, "isMip": false, "isAlpha8": false, "hull": []}, {"name": "Fx\\LavaFallA\\LavaFallA0052", "rect": {"x": 917, "y": 504, "width": 68, "height": 501}, "topLeft": {"x": 30, "y": 25}, "originalSize": {"x": 128, "y": 540}, "scaleRatio": {"x": 1.0, "y": 1.0}, "isMulti": false, "isMip": false, "isAlpha8": false, "hull": []}, {"name": "Fx\\LavaFallA\\LavaFallA0053", "rect": {"x": 917, "y": 1007, "width": 68, "height": 501}, "topLeft": {"x": 30, "y": 25}, "originalSize": {"x": 128, "y": 540}, "scaleRatio": {"x": 1.0, "y": 1.0}, "isMulti": false, "isMip": false, "isAlpha8": false, "hull": []}, {"name": "Fx\\LavaFallA\\LavaFallA0054", "rect": {"x": 986, "y": 1510, "width": 68, "height": 501}, "topLeft": {"x": 30, "y": 25}, "originalSize": {"x": 128, "y": 540}, "scaleRatio": {"x": 1.0, "y": 1.0}, "isMulti": false, "isMip": false, "isAlpha8": false, "hull": []}, {"name": "Fx\\LavaFallA\\LavaFallA0055", "rect": {"x": 987, "y": 504, "width": 68, "height": 501}, "topLeft": {"x": 30, "y": 25}, "originalSize": {"x": 128, "y": 540}, "scaleRatio": {"x": 1.0, "y": 1.0}, "isMulti": false, "isMip": false, "isAlpha8": false, "hull": []}, {"name": "Fx\\LavaFallA\\LavaFallA0056", "rect": {"x": 1056, "y": 1, "width": 68, "height": 501}, "topLeft": {"x": 30, "y": 25}, "originalSize": {"x": 128, "y": 540}, "scaleRatio": {"x": 1.0, "y": 1.0}, "isMulti": false, "isMip": false, "isAlpha8": false, "hull": []}, {"name": "Fx\\LavaFallA\\LavaFallA0057", "rect": {"x": 987, "y": 1007, "width": 68, "height": 501}, "topLeft": {"x": 30, "y": 25}, "originalSize": {"x": 128, "y": 540}, "scaleRatio": {"x": 1.0, "y": 1.0}, "isMulti": false, "isMip": false, "isAlpha8": false, "hull": []}, {"name": "Fx\\LavaFallA\\LavaFallA0058", "rect": {"x": 1056, "y": 1510, "width": 68, "height": 501}, "topLeft": {"x": 30, "y": 25}, "originalSize": {"x": 128, "y": 540}, "scaleRatio": {"x": 1.0, "y": 1.0}, "isMulti": false, "isMip": false, "isAlpha8": false, "hull": []}, {"name": "Fx\\LavaFallA\\LavaFallA0059", "rect": {"x": 1057, "y": 504, "width": 68, "height": 501}, "topLeft": {"x": 30, "y": 25}, "originalSize": {"x": 128, "y": 540}, "scaleRatio": {"x": 1.0, "y": 1.0}, "isMulti": false, "isMip": false, "isAlpha8": false, "hull": []}, {"name": "Fx\\LavaFallA\\LavaFallA0060", "rect": {"x": 1126, "y": 1, "width": 68, "height": 501}, "topLeft": {"x": 30, "y": 25}, "originalSize": {"x": 128, "y": 540}, "scaleRatio": {"x": 1.0, "y": 1.0}, "isMulti": false, "isMip": false, "isAlpha8": false, "hull": []}, {"name": "Fx\\LavaFallA\\LavaFallA0061", "rect": {"x": 1057, "y": 1007, "width": 68, "height": 501}, "topLeft": {"x": 30, "y": 25}, "originalSize": {"x": 128, "y": 540}, "scaleRatio": {"x": 1.0, "y": 1.0}, "isMulti": false, "isMip": false, "isAlpha8": false, "hull": []}, {"name": "Fx\\LavaFallA\\LavaFallA0062", "rect": {"x": 1126, "y": 1510, "width": 68, "height": 501}, "topLeft": {"x": 30, "y": 25}, "originalSize": {"x": 128, "y": 540}, "scaleRatio": {"x": 1.0, "y": 1.0}, "isMulti": false, "isMip": false, "isAlpha8": false, "hull": []}, {"name": "Fx\\LavaFallA\\LavaFallA0063", "rect": {"x": 1127, "y": 504, "width": 68, "height": 501}, "topLeft": {"x": 30, "y": 25}, "originalSize": {"x": 128, "y": 540}, "scaleRatio": {"x": 1.0, "y": 1.0}, "isMulti": false, "isMip": false, "isAlpha8": false, "hull": []}, {"name": "Fx\\LavaFallA\\LavaFallA0064", "rect": {"x": 1196, "y": 1, "width": 68, "height": 501}, "topLeft": {"x": 30, "y": 25}, "originalSize": {"x": 128, "y": 540}, "scaleRatio": {"x": 1.0, "y": 1.0}, "isMulti": false, "isMip": false, "isAlpha8": false, "hull": []}, {"name": "Fx\\LavaFallA\\LavaFallA0065", "rect": {"x": 1127, "y": 1007, "width": 68, "height": 501}, "topLeft": {"x": 30, "y": 25}, "originalSize": {"x": 128, "y": 540}, "scaleRatio": {"x": 1.0, "y": 1.0}, "isMulti": false, "isMip": false, "isAlpha8": false, "hull": []}, {"name": "Fx\\LavaFallA\\LavaFallA0066", "rect": {"x": 1196, "y": 1510, "width": 68, "height": 501}, "topLeft": {"x": 30, "y": 25}, "originalSize": {"x": 128, "y": 540}, "scaleRatio": {"x": 1.0, "y": 1.0}, "isMulti": false, "isMip": false, "isAlpha8": false, "hull": []}, {"name": "Fx\\LavaFallA\\LavaFallA0067", "rect": {"x": 1197, "y": 504, "width": 68, "height": 501}, "topLeft": {"x": 30, "y": 25}, "originalSize": {"x": 128, "y": 540}, "scaleRatio": {"x": 1.0, "y": 1.0}, "isMulti": false, "isMip": false, "isAlpha8": false, "hull": []}, {"name": "Fx\\LavaFallA\\LavaFallA0068", "rect": {"x": 1266, "y": 1, "width": 68, "height": 501}, "topLeft": {"x": 30, "y": 25}, "originalSize": {"x": 128, "y": 540}, "scaleRatio": {"x": 1.0, "y": 1.0}, "isMulti": false, "isMip": false, "isAlpha8": false, "hull": []}, {"name": "Fx\\LavaFallA\\LavaFallA0069", "rect": {"x": 1197, "y": 1007, "width": 68, "height": 501}, "topLeft": {"x": 30, "y": 25}, "originalSize": {"x": 128, "y": 540}, "scaleRatio": {"x": 1.0, "y": 1.0}, "isMulti": false, "isMip": false, "isAlpha8": false, "hull": []}, {"name": "Fx\\LavaFallA\\LavaFallA0070", "rect": {"x": 1266, "y": 1510, "width": 68, "height": 501}, "topLeft": {"x": 30, "y": 25}, "originalSize": {"x": 128, "y": 540}, "scaleRatio": {"x": 1.0, "y": 1.0}, "isMulti": false, "isMip": false, "isAlpha8": false, "hull": []}, {"name": "Fx\\LavaFallA\\LavaFallA0071", "rect": {"x": 1267, "y": 504, "width": 68, "height": 501}, "topLeft": {"x": 30, "y": 25}, "originalSize": {"x": 128, "y": 540}, "scaleRatio": {"x": 1.0, "y": 1.0}, "isMulti": false, "isMip": false, "isAlpha8": false, "hull": []}, {"name": "Fx\\LavaFallA\\LavaFallA0072", "rect": {"x": 1336, "y": 1, "width": 68, "height": 501}, "topLeft": {"x": 30, "y": 25}, "originalSize": {"x": 128, "y": 540}, "scaleRatio": {"x": 1.0, "y": 1.0}, "isMulti": false, "isMip": false, "isAlpha8": false, "hull": []}, {"name": "Fx\\LavaFallA\\LavaFallA0073", "rect": {"x": 1267, "y": 1007, "width": 68, "height": 501}, "topLeft": {"x": 30, "y": 25}, "originalSize": {"x": 128, "y": 540}, "scaleRatio": {"x": 1.0, "y": 1.0}, "isMulti": false, "isMip": false, "isAlpha8": false, "hull": []}, {"name": "Fx\\LavaFallA\\LavaFallA0074", "rect": {"x": 1336, "y": 1510, "width": 68, "height": 501}, "topLeft": {"x": 30, "y": 25}, "originalSize": {"x": 128, "y": 540}, "scaleRatio": {"x": 1.0, "y": 1.0}, "isMulti": false, "isMip": false, "isAlpha8": false, "hull": []}, {"name": "Fx\\LavaFallA\\LavaFallA0075", "rect": {"x": 1337, "y": 504, "width": 68, "height": 501}, "topLeft": {"x": 30, "y": 25}, "originalSize": {"x": 128, "y": 540}, "scaleRatio": {"x": 1.0, "y": 1.0}, "isMulti": false, "isMip": false, "isAlpha8": false, "hull": []}, {"name": "Fx\\LavaFallA\\LavaFallA0076", "rect": {"x": 1406, "y": 1, "width": 68, "height": 501}, "topLeft": {"x": 30, "y": 25}, "originalSize": {"x": 128, "y": 540}, "scaleRatio": {"x": 1.0, "y": 1.0}, "isMulti": false, "isMip": false, "isAlpha8": false, "hull": []}, {"name": "Fx\\LavaFallA\\LavaFallA0077", "rect": {"x": 1337, "y": 1007, "width": 68, "height": 501}, "topLeft": {"x": 30, "y": 25}, "originalSize": {"x": 128, "y": 540}, "scaleRatio": {"x": 1.0, "y": 1.0}, "isMulti": false, "isMip": false, "isAlpha8": false, "hull": []}, {"name": "Fx\\LavaFallA\\LavaFallA0078", "rect": {"x": 1406, "y": 1510, "width": 68, "height": 501}, "topLeft": {"x": 30, "y": 25}, "originalSize": {"x": 128, "y": 540}, "scaleRatio": {"x": 1.0, "y": 1.0}, "isMulti": false, "isMip": false, "isAlpha8": false, "hull": []}, {"name": "Fx\\LavaFallA\\LavaFallA0079", "rect": {"x": 1407, "y": 504, "width": 68, "height": 501}, "topLeft": {"x": 30, "y": 25}, "originalSize": {"x": 128, "y": 540}, "scaleRatio": {"x": 1.0, "y": 1.0}, "isMulti": false, "isMip": false, "isAlpha8": false, "hull": []}, {"name": "Fx\\LavaFallA\\LavaFallA0080", "rect": {"x": 1476, "y": 1, "width": 68, "height": 501}, "topLeft": {"x": 30, "y": 25}, "originalSize": {"x": 128, "y": 540}, "scaleRatio": {"x": 1.0, "y": 1.0}, "isMulti": false, "isMip": false, "isAlpha8": false, "hull": []}, {"name": "Fx\\LavaFallA\\LavaFallA0081", "rect": {"x": 1407, "y": 1007, "width": 68, "height": 501}, "topLeft": {"x": 30, "y": 25}, "originalSize": {"x": 128, "y": 540}, "scaleRatio": {"x": 1.0, "y": 1.0}, "isMulti": false, "isMip": false, "isAlpha8": false, "hull": []}, {"name": "Fx\\LavaFallA\\LavaFallA0082", "rect": {"x": 1476, "y": 1510, "width": 68, "height": 501}, "topLeft": {"x": 30, "y": 25}, "originalSize": {"x": 128, "y": 540}, "scaleRatio": {"x": 1.0, "y": 1.0}, "isMulti": false, "isMip": false, "isAlpha8": false, "hull": []}, {"name": "Fx\\LavaFallA\\LavaFallA0083", "rect": {"x": 1546, "y": 1, "width": 68, "height": 501}, "topLeft": {"x": 30, "y": 25}, "originalSize": {"x": 128, "y": 540}, "scaleRatio": {"x": 1.0, "y": 1.0}, "isMulti": false, "isMip": false, "isAlpha8": false, "hull": []}, {"name": "Fx\\LavaFallA\\LavaFallA0084", "rect": {"x": 1616, "y": 1, "width": 68, "height": 501}, "topLeft": {"x": 30, "y": 25}, "originalSize": {"x": 128, "y": 540}, "scaleRatio": {"x": 1.0, "y": 1.0}, "isMulti": false, "isMip": false, "isAlpha8": false, "hull": []}, {"name": "Fx\\LavaFallA\\LavaFallA0085", "rect": {"x": 1686, "y": 1, "width": 68, "height": 501}, "topLeft": {"x": 30, "y": 25}, "originalSize": {"x": 128, "y": 540}, "scaleRatio": {"x": 1.0, "y": 1.0}, "isMulti": false, "isMip": false, "isAlpha8": false, "hull": []}, {"name": "Fx\\LavaFallA\\LavaFallA0086", "rect": {"x": 1756, "y": 1, "width": 68, "height": 501}, "topLeft": {"x": 30, "y": 25}, "originalSize": {"x": 128, "y": 540}, "scaleRatio": {"x": 1.0, "y": 1.0}, "isMulti": false, "isMip": false, "isAlpha8": false, "hull": []}, {"name": "Fx\\LavaFallA\\LavaFallA0087", "rect": {"x": 1826, "y": 1, "width": 68, "height": 501}, "topLeft": {"x": 30, "y": 25}, "originalSize": {"x": 128, "y": 540}, "scaleRatio": {"x": 1.0, "y": 1.0}, "isMulti": false, "isMip": false, "isAlpha8": false, "hull": []}, {"name": "Fx\\LavaFallA\\LavaFallA0088", "rect": {"x": 1896, "y": 1, "width": 68, "height": 501}, "topLeft": {"x": 30, "y": 25}, "originalSize": {"x": 128, "y": 540}, "scaleRatio": {"x": 1.0, "y": 1.0}, "isMulti": false, "isMip": false, "isAlpha8": false, "hull": []}, {"name": "Fx\\LavaFallA\\LavaFallA0089", "rect": {"x": 1966, "y": 1, "width": 68, "height": 501}, "topLeft": {"x": 30, "y": 25}, "originalSize": {"x": 128, "y": 540}, "scaleRatio": {"x": 1.0, "y": 1.0}, "isMulti": false, "isMip": false, "isAlpha8": false, "hull": []}, {"name": "Fx\\LavaFallA\\LavaFallA0090", "rect": {"x": 1546, "y": 504, "width": 68, "height": 501}, "topLeft": {"x": 30, "y": 25}, "originalSize": {"x": 128, "y": 540}, "scaleRatio": {"x": 1.0, "y": 1.0}, "isMulti": false, "isMip": false, "isAlpha8": false, "hull": []}, {"name": "Fx\\LavaFallA\\LavaFallA0091", "rect": {"x": 1477, "y": 1007, "width": 68, "height": 501}, "topLeft": {"x": 30, "y": 25}, "originalSize": {"x": 128, "y": 540}, "scaleRatio": {"x": 1.0, "y": 1.0}, "isMulti": false, "isMip": false, "isAlpha8": false, "hull": []}, {"name": "Fx\\LavaFallA\\LavaFallA0092", "rect": {"x": 1546, "y": 1510, "width": 68, "height": 501}, "topLeft": {"x": 30, "y": 25}, "originalSize": {"x": 128, "y": 540}, "scaleRatio": {"x": 1.0, "y": 1.0}, "isMulti": false, "isMip": false, "isAlpha8": false, "hull": []}, {"name": "Fx\\LavaFallA\\LavaFallA0093", "rect": {"x": 1547, "y": 1007, "width": 68, "height": 501}, "topLeft": {"x": 30, "y": 25}, "originalSize": {"x": 128, "y": 540}, "scaleRatio": {"x": 1.0, "y": 1.0}, "isMulti": false, "isMip": false, "isAlpha8": false, "hull": []}, {"name": "Fx\\LavaFallA\\LavaFallA0094", "rect": {"x": 1616, "y": 504, "width": 68, "height": 501}, "topLeft": {"x": 30, "y": 25}, "originalSize": {"x": 128, "y": 540}, "scaleRatio": {"x": 1.0, "y": 1.0}, "isMulti": false, "isMip": false, "isAlpha8": false, "hull": []}, {"name": "Fx\\LavaFallA\\LavaFallA0095", "rect": {"x": 1616, "y": 1510, "width": 68, "height": 501}, "topLeft": {"x": 30, "y": 25}, "originalSize": {"x": 128, "y": 540}, "scaleRatio": {"x": 1.0, "y": 1.0}, "isMulti": false, "isMip": false, "isAlpha8": false, "hull": []}, {"name": "Fx\\LavaFallA\\LavaFallA0096", "rect": {"x": 1617, "y": 1007, "width": 68, "height": 501}, "topLeft": {"x": 30, "y": 25}, "originalSize": {"x": 128, "y": 540}, "scaleRatio": {"x": 1.0, "y": 1.0}, "isMulti": false, "isMip": false, "isAlpha8": false, "hull": []}, {"name": "Fx\\LavaFallA\\LavaFallA0097", "rect": {"x": 1686, "y": 504, "width": 68, "height": 501}, "topLeft": {"x": 30, "y": 25}, "originalSize": {"x": 128, "y": 540}, "scaleRatio": {"x": 1.0, "y": 1.0}, "isMulti": false, "isMip": false, "isAlpha8": false, "hull": []}], "isReference": true, "referencedTextureName": "bin\\Win\\Atlases\\Surface_LavaFallA20"}