{"name": "bin\\Win\\Atlases\\Elysium_SoulFlowB49", "version": 4, "subAtlases": [{"name": "Fx\\SoulFlowB\\SoulFlowB0067", "rect": {"x": 1, "y": 1, "width": 129, "height": 173}, "topLeft": {"x": 19, "y": 16}, "originalSize": {"x": 480, "y": 480}, "scaleRatio": {"x": 2.376237630844116, "y": 2.376237630844116}, "isMulti": false, "isMip": true, "isAlpha8": false, "hull": [{"x": 65, "y": -48}, {"x": 65, "y": -39}, {"x": 2, "y": 87}, {"x": 0, "y": 87}, {"x": -57, "y": 43}, {"x": -65, "y": -9}, {"x": -65, "y": -17}, {"x": -27, "y": -69}, {"x": 22, "y": -87}, {"x": 59, "y": -87}]}, {"name": "Fx\\SoulFlowB\\SoulFlowB0055", "rect": {"x": 1, "y": 176, "width": 152, "height": 229}, "topLeft": {"x": 27, "y": 19}, "originalSize": {"x": 480, "y": 480}, "scaleRatio": {"x": 1.7843866348266602, "y": 1.7843866348266602}, "isMulti": false, "isMip": false, "isAlpha8": false, "hull": [{"x": 77, "y": -97}, {"x": 77, "y": -78}, {"x": 1, "y": 115}, {"x": -2, "y": 115}, {"x": -72, "y": 51}, {"x": -77, "y": -27}, {"x": -17, "y": -95}, {"x": 45, "y": -115}, {"x": 50, "y": -115}]}, {"name": "Fx\\SoulFlowB\\SoulFlowB0041", "rect": {"x": 132, "y": 1, "width": 123, "height": 173}, "topLeft": {"x": 21, "y": 10}, "originalSize": {"x": 480, "y": 480}, "scaleRatio": {"x": 2.376237630844116, "y": 2.376237630844116}, "isMulti": false, "isMip": true, "isAlpha8": false, "hull": [{"x": 52, "y": -40}, {"x": -14, "y": 87}, {"x": -17, "y": 87}, {"x": -62, "y": 36}, {"x": -62, "y": 0}, {"x": -59, "y": -24}, {"x": -8, "y": -73}, {"x": 42, "y": -87}]}, {"name": "Fx\\SoulFlowB\\SoulFlowB0077", "rect": {"x": 1, "y": 407, "width": 124, "height": 178}, "topLeft": {"x": 20, "y": 13}, "originalSize": {"x": 480, "y": 480}, "scaleRatio": {"x": 2.376237630844116, "y": 2.376237630844116}, "isMulti": false, "isMip": true, "isAlpha8": false, "hull": [{"x": 63, "y": -34}, {"x": 9, "y": 90}, {"x": 8, "y": 90}, {"x": -52, "y": 50}, {"x": -63, "y": -9}, {"x": -33, "y": -63}, {"x": 40, "y": -90}, {"x": 55, "y": -90}]}, {"name": "Fx\\SoulFlowB\\SoulFlowB0031", "rect": {"x": 1, "y": 587, "width": 120, "height": 174}, "topLeft": {"x": 23, "y": 6}, "originalSize": {"x": 480, "y": 480}, "scaleRatio": {"x": 2.376237630844116, "y": 2.376237630844116}, "isMulti": false, "isMip": true, "isAlpha8": false, "hull": [{"x": 55, "y": -40}, {"x": -21, "y": 88}, {"x": -61, "y": 34}, {"x": -61, "y": 4}, {"x": -56, "y": -27}, {"x": -1, "y": -72}, {"x": 47, "y": -86}]}, {"name": "Fx\\SoulFlowB\\SoulFlowB0057", "rect": {"x": 1, "y": 763, "width": 151, "height": 230}, "topLeft": {"x": 26, "y": 19}, "originalSize": {"x": 480, "y": 480}, "scaleRatio": {"x": 1.7843866348266602, "y": 1.7843866348266602}, "isMulti": false, "isMip": false, "isAlpha8": false, "hull": [{"x": 76, "y": -97}, {"x": 76, "y": -77}, {"x": 3, "y": 116}, {"x": 2, "y": 116}, {"x": -70, "y": 53}, {"x": -76, "y": -14}, {"x": -76, "y": -26}, {"x": -17, "y": -95}, {"x": 50, "y": -115}]}, {"name": "Fx\\SoulFlowB\\SoulFlowB0037", "rect": {"x": 123, "y": 587, "width": 121, "height": 173}, "topLeft": {"x": 22, "y": 9}, "originalSize": {"x": 480, "y": 480}, "scaleRatio": {"x": 2.376237630844116, "y": 2.376237630844116}, "isMulti": false, "isMip": true, "isAlpha8": false, "hull": [{"x": 54, "y": -41}, {"x": -17, "y": 87}, {"x": -61, "y": 36}, {"x": -61, "y": -23}, {"x": -5, "y": -73}, {"x": 39, "y": -87}, {"x": 45, "y": -87}]}, {"name": "Fx\\SoulFlowB\\SoulFlowB0039", "rect": {"x": 127, "y": 407, "width": 121, "height": 172}, "topLeft": {"x": 21, "y": 10}, "originalSize": {"x": 480, "y": 480}, "scaleRatio": {"x": 2.376237630844116, "y": 2.376237630844116}, "isMulti": false, "isMip": true, "isAlpha8": false, "hull": [{"x": 54, "y": -40}, {"x": -14, "y": 87}, {"x": -17, "y": 87}, {"x": -61, "y": 35}, {"x": -61, "y": 3}, {"x": -57, "y": -25}, {"x": -5, "y": -73}, {"x": 40, "y": -87}, {"x": 56, "y": -87}]}, {"name": "Fx\\SoulFlowB\\SoulFlowB0006", "rect": {"x": 155, "y": 176, "width": 120, "height": 153}, "topLeft": {"x": 20, "y": 11}, "originalSize": {"x": 480, "y": 480}, "scaleRatio": {"x": 2.376237630844116, "y": 2.376237630844116}, "isMulti": false, "isMip": true, "isAlpha8": false, "hull": [{"x": 55, "y": -14}, {"x": -30, "y": 77}, {"x": -61, "y": 21}, {"x": -61, "y": 16}, {"x": -41, "y": -35}, {"x": 12, "y": -62}, {"x": 44, "y": -72}]}, {"name": "Fx\\SoulFlowB\\SoulFlowB0042", "rect": {"x": 257, "y": 1, "width": 123, "height": 172}, "topLeft": {"x": 21, "y": 11}, "originalSize": {"x": 480, "y": 480}, "scaleRatio": {"x": 2.376237630844116, "y": 2.376237630844116}, "isMulti": false, "isMip": true, "isAlpha8": false, "hull": [{"x": 62, "y": -69}, {"x": 62, "y": -61}, {"x": -13, "y": 87}, {"x": -16, "y": 87}, {"x": -62, "y": 34}, {"x": -62, "y": 4}, {"x": -59, "y": -24}, {"x": -9, "y": -73}, {"x": 38, "y": -87}]}, {"name": "Fx\\SoulFlowB\\SoulFlowB0007", "rect": {"x": 1, "y": 995, "width": 119, "height": 152}, "topLeft": {"x": 20, "y": 12}, "originalSize": {"x": 480, "y": 480}, "scaleRatio": {"x": 2.376237630844116, "y": 2.376237630844116}, "isMulti": false, "isMip": true, "isAlpha8": false, "hull": [{"x": 54, "y": -15}, {"x": -27, "y": 77}, {"x": -30, "y": 77}, {"x": -60, "y": 23}, {"x": -60, "y": 14}, {"x": -41, "y": -35}, {"x": 13, "y": -62}, {"x": 43, "y": -72}]}, {"name": "Fx\\SoulFlowB\\SoulFlowB0043", "rect": {"x": 1, "y": 1149, "width": 122, "height": 173}, "topLeft": {"x": 21, "y": 11}, "originalSize": {"x": 480, "y": 480}, "scaleRatio": {"x": 2.376237630844116, "y": 2.376237630844116}, "isMulti": false, "isMip": true, "isAlpha8": false, "hull": [{"x": 62, "y": -72}, {"x": 62, "y": -61}, {"x": -13, "y": 87}, {"x": -62, "y": 35}, {"x": -62, "y": 8}, {"x": -58, "y": -24}, {"x": -9, "y": -73}, {"x": 35, "y": -87}, {"x": 39, "y": -87}]}, {"name": "Fx\\SoulFlowB\\SoulFlowB0005", "rect": {"x": 122, "y": 995, "width": 115, "height": 152}, "topLeft": {"x": 20, "y": 11}, "originalSize": {"x": 480, "y": 480}, "scaleRatio": {"x": 2.376237630844116, "y": 2.376237630844116}, "isMulti": false, "isMip": true, "isAlpha8": false, "hull": [{"x": 58, "y": -19}, {"x": 58, "y": -13}, {"x": -27, "y": 77}, {"x": -29, "y": 77}, {"x": -58, "y": 22}, {"x": -58, "y": 17}, {"x": -38, "y": -35}, {"x": 15, "y": -61}, {"x": 47, "y": -72}]}, {"name": "Fx\\SoulFlowB\\SoulFlowB0023", "rect": {"x": 154, "y": 762, "width": 119, "height": 163}, "topLeft": {"x": 21, "y": 12}, "originalSize": {"x": 480, "y": 480}, "scaleRatio": {"x": 2.376237630844116, "y": 2.376237630844116}, "isMulti": false, "isMip": true, "isAlpha8": false, "hull": [{"x": 54, "y": -32}, {"x": -22, "y": 82}, {"x": -24, "y": 82}, {"x": -59, "y": 26}, {"x": -51, "y": -33}, {"x": 6, "y": -74}, {"x": 35, "y": -82}, {"x": 42, "y": -82}]}, {"name": "Fx\\SoulFlowB\\SoulFlowB0017", "rect": {"x": 246, "y": 581, "width": 115, "height": 161}, "topLeft": {"x": 20, "y": 10}, "originalSize": {"x": 480, "y": 480}, "scaleRatio": {"x": 2.376237630844116, "y": 2.376237630844116}, "isMulti": false, "isMip": true, "isAlpha8": false, "hull": [{"x": 50, "y": -14}, {"x": -21, "y": 81}, {"x": -24, "y": 81}, {"x": -57, "y": 23}, {"x": -46, "y": -34}, {"x": 12, "y": -73}, {"x": 48, "y": -81}, {"x": 52, "y": -81}]}, {"name": "Fx\\SoulFlowB\\SoulFlowB0045", "rect": {"x": 250, "y": 331, "width": 121, "height": 172}, "topLeft": {"x": 21, "y": 12}, "originalSize": {"x": 480, "y": 480}, "scaleRatio": {"x": 2.376237630844116, "y": 2.376237630844116}, "isMulti": false, "isMip": true, "isAlpha8": false, "hull": [{"x": 61, "y": -71}, {"x": 61, "y": -60}, {"x": -10, "y": 87}, {"x": -13, "y": 87}, {"x": -61, "y": 34}, {"x": -61, "y": -1}, {"x": -59, "y": -23}, {"x": -10, "y": -73}, {"x": 37, "y": -87}]}, {"name": "Fx\\SoulFlowB\\SoulFlowB0008", "rect": {"x": 277, "y": 175, "width": 118, "height": 153}, "topLeft": {"x": 20, "y": 12}, "originalSize": {"x": 480, "y": 480}, "scaleRatio": {"x": 2.376237630844116, "y": 2.376237630844116}, "isMulti": false, "isMip": true, "isAlpha8": false, "hull": [{"x": 60, "y": -67}, {"x": 54, "y": -15}, {"x": -27, "y": 77}, {"x": -29, "y": 77}, {"x": -60, "y": 22}, {"x": -60, "y": 14}, {"x": -42, "y": -35}, {"x": 36, "y": -74}]}, {"name": "Fx\\SoulFlowB\\SoulFlowB0022", "rect": {"x": 382, "y": 1, "width": 120, "height": 164}, "topLeft": {"x": 21, "y": 11}, "originalSize": {"x": 480, "y": 480}, "scaleRatio": {"x": 2.376237630844116, "y": 2.376237630844116}, "isMulti": false, "isMip": true, "isAlpha8": false, "hull": [{"x": 55, "y": -32}, {"x": -24, "y": 83}, {"x": -61, "y": 25}, {"x": -51, "y": -34}, {"x": 6, "y": -74}, {"x": 42, "y": -82}]}, {"name": "Fx\\SoulFlowB\\SoulFlowB0040", "rect": {"x": 1, "y": 1324, "width": 120, "height": 173}, "topLeft": {"x": 21, "y": 10}, "originalSize": {"x": 480, "y": 480}, "scaleRatio": {"x": 2.376237630844116, "y": 2.376237630844116}, "isMulti": false, "isMip": true, "isAlpha8": false, "hull": [{"x": 61, "y": -72}, {"x": 61, "y": -53}, {"x": -14, "y": 87}, {"x": -61, "y": 33}, {"x": -61, "y": 6}, {"x": -57, "y": -25}, {"x": -6, "y": -73}, {"x": 38, "y": -87}, {"x": 42, "y": -87}]}, {"name": "Fx\\SoulFlowB\\SoulFlowB0082", "rect": {"x": 1, "y": 1499, "width": 120, "height": 157}, "topLeft": {"x": 22, "y": 13}, "originalSize": {"x": 480, "y": 480}, "scaleRatio": {"x": 2.376237630844116, "y": 2.376237630844116}, "isMulti": false, "isMip": true, "isAlpha8": false, "hull": [{"x": 61, "y": -22}, {"x": 6, "y": 63}, {"x": -28, "y": 77}, {"x": -61, "y": 38}, {"x": -61, "y": 2}, {"x": -37, "y": -49}, {"x": 40, "y": -79}, {"x": 51, "y": -79}]}, {"name": "Fx\\SoulFlowB\\SoulFlowB0027", "rect": {"x": 1, "y": 1658, "width": 118, "height": 173}, "topLeft": {"x": 22, "y": 5}, "originalSize": {"x": 480, "y": 480}, "scaleRatio": {"x": 2.376237630844116, "y": 2.376237630844116}, "isMulti": false, "isMip": true, "isAlpha8": false, "hull": [{"x": 46, "y": -22}, {"x": -21, "y": 87}, {"x": -60, "y": 32}, {"x": -60, "y": 24}, {"x": -53, "y": -29}, {"x": 3, "y": -72}, {"x": 54, "y": -86}]}, {"name": "Fx\\SoulFlowB\\SoulFlowB0030", "rect": {"x": 1, "y": 1833, "width": 117, "height": 173}, "topLeft": {"x": 22, "y": 6}, "originalSize": {"x": 480, "y": 480}, "scaleRatio": {"x": 2.376237630844116, "y": 2.376237630844116}, "isMulti": false, "isMip": true, "isAlpha8": false, "hull": [{"x": 59, "y": -44}, {"x": 59, "y": -37}, {"x": -18, "y": 87}, {"x": -20, "y": 87}, {"x": -59, "y": 33}, {"x": -59, "y": 23}, {"x": -53, "y": -28}, {"x": 2, "y": -72}, {"x": 47, "y": -87}, {"x": 50, "y": -87}]}, {"name": "Fx\\SoulFlowB\\SoulFlowB0044", "rect": {"x": 120, "y": 1833, "width": 121, "height": 173}, "topLeft": {"x": 21, "y": 11}, "originalSize": {"x": 480, "y": 480}, "scaleRatio": {"x": 2.376237630844116, "y": 2.376237630844116}, "isMulti": false, "isMip": true, "isAlpha8": false, "hull": [{"x": 61, "y": -72}, {"x": 61, "y": -59}, {"x": -12, "y": 87}, {"x": -13, "y": 87}, {"x": -61, "y": 35}, {"x": -61, "y": -1}, {"x": -59, "y": -23}, {"x": -9, "y": -73}, {"x": 38, "y": -86}]}, {"name": "Fx\\SoulFlowB\\SoulFlowB0024", "rect": {"x": 121, "y": 1658, "width": 119, "height": 170}, "topLeft": {"x": 21, "y": 6}, "originalSize": {"x": 480, "y": 480}, "scaleRatio": {"x": 2.376237630844116, "y": 2.376237630844116}, "isMulti": false, "isMip": true, "isAlpha8": false, "hull": [{"x": 54, "y": -30}, {"x": -21, "y": 86}, {"x": -23, "y": 86}, {"x": -59, "y": 29}, {"x": -52, "y": -30}, {"x": 6, "y": -71}, {"x": 41, "y": -79}]}, {"name": "Fx\\SoulFlowB\\SoulFlowB0032", "rect": {"x": 123, "y": 1324, "width": 115, "height": 173}, "topLeft": {"x": 23, "y": 7}, "originalSize": {"x": 480, "y": 480}, "scaleRatio": {"x": 2.376237630844116, "y": 2.376237630844116}, "isMulti": false, "isMip": true, "isAlpha8": false, "hull": [{"x": 58, "y": -45}, {"x": 58, "y": -38}, {"x": -17, "y": 87}, {"x": -19, "y": 87}, {"x": -58, "y": 36}, {"x": -58, "y": -2}, {"x": -54, "y": -27}, {"x": 1, "y": -72}, {"x": 46, "y": -87}, {"x": 49, "y": -87}]}, {"name": "Fx\\SoulFlowB\\SoulFlowB0046", "rect": {"x": 125, "y": 1149, "width": 120, "height": 172}, "topLeft": {"x": 21, "y": 12}, "originalSize": {"x": 480, "y": 480}, "scaleRatio": {"x": 2.376237630844116, "y": 2.376237630844116}, "isMulti": false, "isMip": true, "isAlpha8": false, "hull": [{"x": 61, "y": -70}, {"x": 61, "y": -62}, {"x": -9, "y": 87}, {"x": -12, "y": 87}, {"x": -61, "y": 34}, {"x": -61, "y": 10}, {"x": -58, "y": -23}, {"x": -10, "y": -73}, {"x": 37, "y": -87}]}, {"name": "Fx\\SoulFlowB\\SoulFlowB0025", "rect": {"x": 239, "y": 927, "width": 118, "height": 164}, "topLeft": {"x": 22, "y": 12}, "originalSize": {"x": 480, "y": 480}, "scaleRatio": {"x": 2.376237630844116, "y": 2.376237630844116}, "isMulti": false, "isMip": true, "isAlpha8": false, "hull": [{"x": 52, "y": -33}, {"x": -21, "y": 83}, {"x": -23, "y": 83}, {"x": -60, "y": 28}, {"x": -60, "y": 20}, {"x": -52, "y": -33}, {"x": 5, "y": -74}, {"x": 40, "y": -82}]}, {"name": "Fx\\SoulFlowB\\SoulFlowB0084", "rect": {"x": 275, "y": 744, "width": 119, "height": 158}, "topLeft": {"x": 22, "y": 13}, "originalSize": {"x": 480, "y": 480}, "scaleRatio": {"x": 2.376237630844116, "y": 2.376237630844116}, "isMulti": false, "isMip": true, "isAlpha8": false, "hull": [{"x": 60, "y": -27}, {"x": 60, "y": -20}, {"x": 7, "y": 63}, {"x": -35, "y": 80}, {"x": -46, "y": 80}, {"x": -60, "y": 10}, {"x": -60, "y": 4}, {"x": -20, "y": -52}, {"x": 39, "y": -80}, {"x": 50, "y": -80}]}, {"name": "Fx\\SoulFlowB\\SoulFlowB0047", "rect": {"x": 363, "y": 505, "width": 119, "height": 173}, "topLeft": {"x": 21, "y": 12}, "originalSize": {"x": 480, "y": 480}, "scaleRatio": {"x": 2.376237630844116, "y": 2.376237630844116}, "isMulti": false, "isMip": true, "isAlpha8": false, "hull": [{"x": 60, "y": -72}, {"x": 60, "y": -58}, {"x": -8, "y": 87}, {"x": -60, "y": 35}, {"x": -60, "y": 6}, {"x": -58, "y": -22}, {"x": -10, "y": -73}, {"x": 38, "y": -86}]}, {"name": "Fx\\SoulFlowB\\SoulFlowB0036", "rect": {"x": 373, "y": 330, "width": 117, "height": 173}, "topLeft": {"x": 22, "y": 8}, "originalSize": {"x": 480, "y": 480}, "scaleRatio": {"x": 2.376237630844116, "y": 2.376237630844116}, "isMulti": false, "isMip": true, "isAlpha8": false, "hull": [{"x": 56, "y": -40}, {"x": -15, "y": 87}, {"x": -18, "y": 87}, {"x": -59, "y": 35}, {"x": -59, "y": 2}, {"x": -55, "y": -26}, {"x": -2, "y": -72}, {"x": 45, "y": -86}]}, {"name": "Fx\\SoulFlowB\\SoulFlowB0015", "rect": {"x": 397, "y": 167, "width": 116, "height": 160}, "topLeft": {"x": 20, "y": 10}, "originalSize": {"x": 480, "y": 480}, "scaleRatio": {"x": 2.376237630844116, "y": 2.376237630844116}, "isMulti": false, "isMip": true, "isAlpha8": false, "hull": [{"x": 50, "y": -14}, {"x": -24, "y": 81}, {"x": -58, "y": 22}, {"x": -45, "y": -35}, {"x": 12, "y": -73}, {"x": 54, "y": -81}]}, {"name": "Fx\\SoulFlowB\\SoulFlowB0013", "rect": {"x": 504, "y": 1, "width": 113, "height": 158}, "topLeft": {"x": 20, "y": 10}, "originalSize": {"x": 480, "y": 480}, "scaleRatio": {"x": 2.376237630844116, "y": 2.376237630844116}, "isMulti": false, "isMip": true, "isAlpha8": false, "hull": [{"x": 56, "y": -67}, {"x": 54, "y": -14}, {"x": -21, "y": 80}, {"x": -24, "y": 80}, {"x": -57, "y": 23}, {"x": -57, "y": 18}, {"x": -42, "y": -35}, {"x": 43, "y": -76}]}, {"name": "Fx\\SoulFlowB\\SoulFlowB0048", "rect": {"x": 240, "y": 1323, "width": 118, "height": 172}, "topLeft": {"x": 21, "y": 13}, "originalSize": {"x": 480, "y": 480}, "scaleRatio": {"x": 2.376237630844116, "y": 2.376237630844116}, "isMulti": false, "isMip": true, "isAlpha8": false, "hull": [{"x": 60, "y": -73}, {"x": 60, "y": -59}, {"x": -7, "y": 87}, {"x": -8, "y": 87}, {"x": -60, "y": 34}, {"x": -60, "y": 15}, {"x": -58, "y": -22}, {"x": -11, "y": -73}, {"x": 37, "y": -87}]}, {"name": "Fx\\SoulFlowB\\SoulFlowB0014", "rect": {"x": 240, "y": 1497, "width": 112, "height": 159}, "topLeft": {"x": 20, "y": 10}, "originalSize": {"x": 480, "y": 480}, "scaleRatio": {"x": 2.376237630844116, "y": 2.376237630844116}, "isMulti": false, "isMip": true, "isAlpha8": false, "hull": [{"x": 57, "y": -66}, {"x": 53, "y": -14}, {"x": -20, "y": 80}, {"x": -23, "y": 80}, {"x": -57, "y": 21}, {"x": -43, "y": -35}, {"x": 43, "y": -77}]}, {"name": "Fx\\SoulFlowB\\SoulFlowB0011", "rect": {"x": 123, "y": 1499, "width": 115, "height": 154}, "topLeft": {"x": 20, "y": 13}, "originalSize": {"x": 480, "y": 480}, "scaleRatio": {"x": 2.376237630844116, "y": 2.376237630844116}, "isMulti": false, "isMip": true, "isAlpha8": false, "hull": [{"x": 54, "y": -16}, {"x": -24, "y": 78}, {"x": -26, "y": 78}, {"x": -58, "y": 22}, {"x": -58, "y": 13}, {"x": -42, "y": -36}, {"x": 15, "y": -74}, {"x": 57, "y": -78}]}, {"name": "Fx\\SoulFlowB\\SoulFlowB0026", "rect": {"x": 242, "y": 1658, "width": 118, "height": 171}, "topLeft": {"x": 22, "y": 6}, "originalSize": {"x": 480, "y": 480}, "scaleRatio": {"x": 2.376237630844116, "y": 2.376237630844116}, "isMulti": false, "isMip": true, "isAlpha8": false, "hull": [{"x": 52, "y": -31}, {"x": -21, "y": 86}, {"x": -23, "y": 86}, {"x": -60, "y": 32}, {"x": -60, "y": 24}, {"x": -53, "y": -29}, {"x": 4, "y": -71}, {"x": 39, "y": -79}]}, {"name": "Fx\\SoulFlowB\\SoulFlowB0085", "rect": {"x": 354, "y": 1497, "width": 118, "height": 157}, "topLeft": {"x": 22, "y": 14}, "originalSize": {"x": 480, "y": 480}, "scaleRatio": {"x": 2.376237630844116, "y": 2.376237630844116}, "isMulti": false, "isMip": true, "isAlpha8": false, "hull": [{"x": 60, "y": -27}, {"x": 60, "y": -21}, {"x": -36, "y": 65}, {"x": -51, "y": 49}, {"x": -60, "y": 10}, {"x": -60, "y": 5}, {"x": -20, "y": -53}, {"x": 36, "y": -79}, {"x": 50, "y": -79}]}, {"name": "Fx\\SoulFlowB\\SoulFlowB0016", "rect": {"x": 243, "y": 1831, "width": 116, "height": 160}, "topLeft": {"x": 20, "y": 10}, "originalSize": {"x": 480, "y": 480}, "scaleRatio": {"x": 2.376237630844116, "y": 2.376237630844116}, "isMulti": false, "isMip": true, "isAlpha8": false, "hull": [{"x": 50, "y": -14}, {"x": -21, "y": 81}, {"x": -24, "y": 81}, {"x": -58, "y": 23}, {"x": -46, "y": -34}, {"x": 12, "y": -73}, {"x": 53, "y": -81}]}, {"name": "Fx\\SoulFlowB\\SoulFlowB0033", "rect": {"x": 361, "y": 1831, "width": 115, "height": 173}, "topLeft": {"x": 23, "y": 7}, "originalSize": {"x": 480, "y": 480}, "scaleRatio": {"x": 2.376237630844116, "y": 2.376237630844116}, "isMulti": false, "isMip": true, "isAlpha8": false, "hull": [{"x": 58, "y": -44}, {"x": 58, "y": -38}, {"x": -17, "y": 87}, {"x": -20, "y": 87}, {"x": -58, "y": 36}, {"x": -58, "y": -24}, {"x": 0, "y": -72}, {"x": 44, "y": -87}, {"x": 47, "y": -87}]}, {"name": "Fx\\SoulFlowB\\SoulFlowB0086", "rect": {"x": 362, "y": 1656, "width": 118, "height": 157}, "topLeft": {"x": 22, "y": 14}, "originalSize": {"x": 480, "y": 480}, "scaleRatio": {"x": 2.376237630844116, "y": 2.376237630844116}, "isMulti": false, "isMip": true, "isAlpha8": false, "hull": [{"x": 60, "y": -22}, {"x": -36, "y": 66}, {"x": -51, "y": 49}, {"x": -60, "y": 11}, {"x": -60, "y": 6}, {"x": -21, "y": -52}, {"x": 35, "y": -79}, {"x": 49, "y": -79}]}, {"name": "Fx\\SoulFlowB\\SoulFlowB0035", "rect": {"x": 247, "y": 1093, "width": 115, "height": 173}, "topLeft": {"x": 22, "y": 8}, "originalSize": {"x": 480, "y": 480}, "scaleRatio": {"x": 2.376237630844116, "y": 2.376237630844116}, "isMulti": false, "isMip": true, "isAlpha8": false, "hull": [{"x": 58, "y": -44}, {"x": 58, "y": -38}, {"x": -14, "y": 87}, {"x": -17, "y": 87}, {"x": -58, "y": 34}, {"x": -58, "y": 2}, {"x": -54, "y": -26}, {"x": -1, "y": -72}, {"x": 44, "y": -87}, {"x": 47, "y": -87}]}, {"name": "Fx\\SoulFlowB\\SoulFlowB0009", "rect": {"x": 359, "y": 904, "width": 117, "height": 153}, "topLeft": {"x": 20, "y": 12}, "originalSize": {"x": 480, "y": 480}, "scaleRatio": {"x": 2.376237630844116, "y": 2.376237630844116}, "isMulti": false, "isMip": true, "isAlpha8": false, "hull": [{"x": 54, "y": -15}, {"x": -24, "y": 77}, {"x": -29, "y": 77}, {"x": -59, "y": 23}, {"x": -59, "y": 13}, {"x": -42, "y": -34}, {"x": 12, "y": -62}, {"x": 46, "y": -76}]}, {"name": "Fx\\SoulFlowB\\SoulFlowB0049", "rect": {"x": 396, "y": 680, "width": 117, "height": 172}, "topLeft": {"x": 21, "y": 13}, "originalSize": {"x": 480, "y": 480}, "scaleRatio": {"x": 2.376237630844116, "y": 2.376237630844116}, "isMulti": false, "isMip": true, "isAlpha8": false, "hull": [{"x": 59, "y": -74}, {"x": 59, "y": -57}, {"x": -6, "y": 87}, {"x": -7, "y": 87}, {"x": -59, "y": 35}, {"x": -59, "y": -4}, {"x": -58, "y": -22}, {"x": -11, "y": -72}, {"x": 37, "y": -87}]}, {"name": "Fx\\SoulFlowB\\SoulFlowB0050", "rect": {"x": 484, "y": 505, "width": 117, "height": 172}, "topLeft": {"x": 21, "y": 13}, "originalSize": {"x": 480, "y": 480}, "scaleRatio": {"x": 2.376237630844116, "y": 2.376237630844116}, "isMulti": false, "isMip": true, "isAlpha8": false, "hull": [{"x": 59, "y": -72}, {"x": 59, "y": -58}, {"x": -4, "y": 87}, {"x": -7, "y": 87}, {"x": -59, "y": 36}, {"x": -59, "y": -22}, {"x": -12, "y": -72}, {"x": 36, "y": -87}]}, {"name": "Fx\\SoulFlowB\\SoulFlowB0001", "rect": {"x": 492, "y": 329, "width": 116, "height": 145}, "topLeft": {"x": 21, "y": 15}, "originalSize": {"x": 480, "y": 480}, "scaleRatio": {"x": 2.376237630844116, "y": 2.376237630844116}, "isMulti": false, "isMip": true, "isAlpha8": false, "hull": [{"x": 59, "y": -20}, {"x": 59, "y": -14}, {"x": -29, "y": 73}, {"x": -33, "y": 73}, {"x": -59, "y": 19}, {"x": -59, "y": 12}, {"x": -22, "y": -44}, {"x": 16, "y": -64}, {"x": 45, "y": -73}, {"x": 48, "y": -73}]}, {"name": "Fx\\SoulFlowB\\SoulFlowB0010", "rect": {"x": 515, "y": 161, "width": 116, "height": 153}, "topLeft": {"x": 20, "y": 13}, "originalSize": {"x": 480, "y": 480}, "scaleRatio": {"x": 2.376237630844116, "y": 2.376237630844116}, "isMulti": false, "isMip": true, "isAlpha8": false, "hull": [{"x": 57, "y": -68}, {"x": 54, "y": -16}, {"x": -24, "y": 77}, {"x": -27, "y": 77}, {"x": -59, "y": 21}, {"x": -59, "y": 16}, {"x": -42, "y": -36}, {"x": 41, "y": -77}, {"x": 47, "y": -77}]}, {"name": "Fx\\SoulFlowB\\SoulFlowB0087", "rect": {"x": 619, "y": 1, "width": 117, "height": 157}, "topLeft": {"x": 22, "y": 14}, "originalSize": {"x": 480, "y": 480}, "scaleRatio": {"x": 2.376237630844116, "y": 2.376237630844116}, "isMulti": false, "isMip": true, "isAlpha8": false, "hull": [{"x": 59, "y": -26}, {"x": 59, "y": -20}, {"x": -36, "y": 67}, {"x": -59, "y": 16}, {"x": -59, "y": 5}, {"x": -21, "y": -51}, {"x": 17, "y": -70}, {"x": 46, "y": -79}, {"x": 49, "y": -79}]}, {"name": "Fx\\SoulFlowB\\SoulFlowB0038", "rect": {"x": 360, "y": 1268, "width": 115, "height": 173}, "topLeft": {"x": 21, "y": 9}, "originalSize": {"x": 480, "y": 480}, "scaleRatio": {"x": 2.376237630844116, "y": 2.376237630844116}, "isMulti": false, "isMip": true, "isAlpha8": false, "hull": [{"x": 58, "y": -44}, {"x": 58, "y": -38}, {"x": -12, "y": 87}, {"x": -15, "y": 87}, {"x": -58, "y": 34}, {"x": -58, "y": 13}, {"x": -54, "y": -25}, {"x": -2, "y": -73}, {"x": 42, "y": -87}, {"x": 48, "y": -87}]}, {"name": "Fx\\SoulFlowB\\SoulFlowB0052", "rect": {"x": 364, "y": 1059, "width": 115, "height": 172}, "topLeft": {"x": 21, "y": 14}, "originalSize": {"x": 480, "y": 480}, "scaleRatio": {"x": 2.376237630844116, "y": 2.376237630844116}, "isMulti": false, "isMip": true, "isAlpha8": false, "hull": [{"x": 58, "y": -73}, {"x": 58, "y": -58}, {"x": -3, "y": 87}, {"x": -4, "y": 87}, {"x": -58, "y": 35}, {"x": -58, "y": -23}, {"x": -12, "y": -72}, {"x": 34, "y": -87}, {"x": 38, "y": -87}]}, {"name": "Fx\\SoulFlowB\\SoulFlowB0018", "rect": {"x": 478, "y": 854, "width": 113, "height": 161}, "topLeft": {"x": 21, "y": 11}, "originalSize": {"x": 480, "y": 480}, "scaleRatio": {"x": 2.376237630844116, "y": 2.376237630844116}, "isMulti": false, "isMip": true, "isAlpha8": false, "hull": [{"x": 57, "y": -49}, {"x": 57, "y": -25}, {"x": -21, "y": 81}, {"x": -23, "y": 81}, {"x": -57, "y": 26}, {"x": -57, "y": 14}, {"x": -46, "y": -34}, {"x": 12, "y": -74}, {"x": 43, "y": -81}, {"x": 47, "y": -81}]}, {"name": "Fx\\SoulFlowB\\SoulFlowB0051", "rect": {"x": 515, "y": 679, "width": 116, "height": 173}, "topLeft": {"x": 21, "y": 13}, "originalSize": {"x": 480, "y": 480}, "scaleRatio": {"x": 2.376237630844116, "y": 2.376237630844116}, "isMulti": false, "isMip": true, "isAlpha8": false, "hull": [{"x": 59, "y": -73}, {"x": 59, "y": -58}, {"x": -4, "y": 87}, {"x": -58, "y": 36}, {"x": -59, "y": -21}, {"x": -12, "y": -73}, {"x": 37, "y": -86}]}, {"name": "Fx\\SoulFlowB\\SoulFlowB0004", "rect": {"x": 603, "y": 476, "width": 116, "height": 149}, "topLeft": {"x": 20, "y": 13}, "originalSize": {"x": 480, "y": 480}, "scaleRatio": {"x": 2.376237630844116, "y": 2.376237630844116}, "isMulti": false, "isMip": true, "isAlpha8": false, "hull": [{"x": 58, "y": -15}, {"x": -27, "y": 75}, {"x": -30, "y": 75}, {"x": -59, "y": 21}, {"x": -59, "y": 17}, {"x": -38, "y": -35}, {"x": 16, "y": -62}, {"x": 47, "y": -72}]}, {"name": "Fx\\SoulFlowB\\SoulFlowB0002", "rect": {"x": 610, "y": 316, "width": 116, "height": 148}, "topLeft": {"x": 21, "y": 13}, "originalSize": {"x": 480, "y": 480}, "scaleRatio": {"x": 2.376237630844116, "y": 2.376237630844116}, "isMulti": false, "isMip": true, "isAlpha8": false, "hull": [{"x": 59, "y": -15}, {"x": -30, "y": 75}, {"x": -32, "y": 75}, {"x": -59, "y": 22}, {"x": -59, "y": 11}, {"x": -23, "y": -43}, {"x": 16, "y": -62}, {"x": 47, "y": -72}]}, {"name": "Fx\\SoulFlowB\\SoulFlowB0012", "rect": {"x": 633, "y": 160, "width": 114, "height": 154}, "topLeft": {"x": 20, "y": 13}, "originalSize": {"x": 480, "y": 480}, "scaleRatio": {"x": 2.376237630844116, "y": 2.376237630844116}, "isMulti": false, "isMip": true, "isAlpha8": false, "hull": [{"x": 56, "y": -68}, {"x": 53, "y": -15}, {"x": -22, "y": 78}, {"x": -25, "y": 78}, {"x": -58, "y": 21}, {"x": -58, "y": 16}, {"x": -42, "y": -36}, {"x": 43, "y": -77}]}, {"name": "Fx\\SoulFlowB\\SoulFlowB0003", "rect": {"x": 738, "y": 1, "width": 115, "height": 147}, "topLeft": {"x": 21, "y": 15}, "originalSize": {"x": 480, "y": 480}, "scaleRatio": {"x": 2.376237630844116, "y": 2.376237630844116}, "isMulti": false, "isMip": true, "isAlpha8": false, "hull": [{"x": 58, "y": -21}, {"x": 58, "y": -15}, {"x": -30, "y": 74}, {"x": -58, "y": 22}, {"x": -58, "y": 9}, {"x": -23, "y": -44}, {"x": 16, "y": -64}, {"x": 47, "y": -73}]}, {"name": "Fx\\SoulFlowB\\SoulFlowB0019", "rect": {"x": 474, "y": 1443, "width": 113, "height": 161}, "topLeft": {"x": 21, "y": 11}, "originalSize": {"x": 480, "y": 480}, "scaleRatio": {"x": 2.376237630844116, "y": 2.376237630844116}, "isMulti": false, "isMip": true, "isAlpha8": false, "hull": [{"x": 51, "y": -67}, {"x": 49, "y": -15}, {"x": -20, "y": 81}, {"x": -24, "y": 81}, {"x": -57, "y": 26}, {"x": -57, "y": 19}, {"x": -47, "y": -34}, {"x": 40, "y": -81}, {"x": 45, "y": -81}]}, {"name": "Fx\\SoulFlowB\\SoulFlowB0053", "rect": {"x": 477, "y": 1233, "width": 116, "height": 172}, "topLeft": {"x": 20, "y": 14}, "originalSize": {"x": 480, "y": 480}, "scaleRatio": {"x": 2.376237630844116, "y": 2.376237630844116}, "isMulti": false, "isMip": true, "isAlpha8": false, "hull": [{"x": 59, "y": -73}, {"x": 59, "y": -60}, {"x": -2, "y": 87}, {"x": -3, "y": 87}, {"x": -56, "y": 37}, {"x": -58, "y": -21}, {"x": -12, "y": -72}, {"x": 34, "y": -87}, {"x": 38, "y": -87}]}, {"name": "Fx\\SoulFlowB\\SoulFlowB0054", "rect": {"x": 481, "y": 1017, "width": 115, "height": 172}, "topLeft": {"x": 20, "y": 14}, "originalSize": {"x": 480, "y": 480}, "scaleRatio": {"x": 2.376237630844116, "y": 2.376237630844116}, "isMulti": false, "isMip": true, "isAlpha8": false, "hull": [{"x": 58, "y": -73}, {"x": 58, "y": -58}, {"x": -1, "y": 87}, {"x": -2, "y": 87}, {"x": -54, "y": 38}, {"x": -58, "y": -8}, {"x": -58, "y": -21}, {"x": -12, "y": -72}, {"x": 36, "y": -87}]}, {"name": "Fx\\SoulFlowB\\SoulFlowB0088", "rect": {"x": 593, "y": 854, "width": 117, "height": 145}, "topLeft": {"x": 22, "y": 14}, "originalSize": {"x": 480, "y": 480}, "scaleRatio": {"x": 2.376237630844116, "y": 2.376237630844116}, "isMulti": false, "isMip": true, "isAlpha8": false, "hull": [{"x": 59, "y": -20}, {"x": 59, "y": -14}, {"x": -35, "y": 73}, {"x": -59, "y": 21}, {"x": -59, "y": 10}, {"x": -22, "y": -45}, {"x": 17, "y": -64}, {"x": 45, "y": -73}, {"x": 48, "y": -73}]}, {"name": "Fx\\SoulFlowB\\SoulFlowB0055", "rect": {"x": 633, "y": 627, "width": 114, "height": 173}, "topLeft": {"x": 20, "y": 14}, "originalSize": {"x": 480, "y": 480}, "scaleRatio": {"x": 2.376237630844116, "y": 2.376237630844116}, "isMulti": false, "isMip": true, "isAlpha8": false, "hull": [{"x": 58, "y": -74}, {"x": 58, "y": -58}, {"x": 0, "y": 87}, {"x": -54, "y": 39}, {"x": -58, "y": -20}, {"x": -12, "y": -72}, {"x": 33, "y": -87}, {"x": 38, "y": -87}]}, {"name": "Fx\\SoulFlowB\\SoulFlowB0089", "rect": {"x": 721, "y": 466, "width": 116, "height": 145}, "topLeft": {"x": 22, "y": 14}, "originalSize": {"x": 480, "y": 480}, "scaleRatio": {"x": 2.376237630844116, "y": 2.376237630844116}, "isMulti": false, "isMip": true, "isAlpha8": false, "hull": [{"x": 59, "y": -20}, {"x": 59, "y": -14}, {"x": -32, "y": 73}, {"x": -35, "y": 73}, {"x": -59, "y": 21}, {"x": -59, "y": 10}, {"x": -22, "y": -44}, {"x": 16, "y": -63}, {"x": 48, "y": -72}]}, {"name": "Fx\\SoulFlowB\\SoulFlowB0090", "rect": {"x": 728, "y": 316, "width": 117, "height": 145}, "topLeft": {"x": 21, "y": 15}, "originalSize": {"x": 480, "y": 480}, "scaleRatio": {"x": 2.376237630844116, "y": 2.376237630844116}, "isMulti": false, "isMip": true, "isAlpha8": false, "hull": [{"x": 59, "y": -21}, {"x": 59, "y": -15}, {"x": -32, "y": 73}, {"x": -33, "y": 73}, {"x": -59, "y": 19}, {"x": -59, "y": 12}, {"x": -22, "y": -44}, {"x": 16, "y": -64}, {"x": 45, "y": -73}, {"x": 48, "y": -73}]}, {"name": "Fx\\SoulFlowB\\SoulFlowB0056", "rect": {"x": 478, "y": 1815, "width": 114, "height": 173}, "topLeft": {"x": 20, "y": 14}, "originalSize": {"x": 480, "y": 480}, "scaleRatio": {"x": 2.376237630844116, "y": 2.376237630844116}, "isMulti": false, "isMip": true, "isAlpha8": false, "hull": [{"x": 58, "y": -73}, {"x": 58, "y": -60}, {"x": 1, "y": 87}, {"x": -54, "y": 39}, {"x": -58, "y": -20}, {"x": -13, "y": -71}, {"x": 33, "y": -87}, {"x": 37, "y": -87}]}, {"name": "Fx\\SoulFlowB\\SoulFlowB0057", "rect": {"x": 482, "y": 1606, "width": 114, "height": 173}, "topLeft": {"x": 19, "y": 14}, "originalSize": {"x": 480, "y": 480}, "scaleRatio": {"x": 2.376237630844116, "y": 2.376237630844116}, "isMulti": false, "isMip": true, "isAlpha8": false, "hull": [{"x": 58, "y": -73}, {"x": 58, "y": -59}, {"x": 3, "y": 87}, {"x": 2, "y": 87}, {"x": -53, "y": 39}, {"x": -57, "y": -19}, {"x": -13, "y": -71}, {"x": 38, "y": -86}]}], "isReference": true, "referencedTextureName": "bin\\Win\\Atlases\\Elysium_SoulFlowB49"}