<?xml version="1.0" encoding="UTF-8"?>
<objects serializationModel="Studio.02.02.00">
	<object class="AudioFile" id="{5b8be55a-7984-4ce4-a1c5-bfb977119478}">
		<property name="assetPath">
			<value>ZagreusField_2745.ogg</value>
		</property>
		<property name="frequencyInKHz">
			<value>32</value>
		</property>
		<property name="channelCount">
			<value>1</value>
		</property>
		<property name="length">
			<value>7.774</value>
		</property>
		<relationship name="masterAssetFolder">
			<destination>{bb31ee21-3abf-4df1-9c43-d5c3e0a3a024}</destination>
		</relationship>
	</object>
</objects>
