<?xml version="1.0" encoding="UTF-8"?>
<objects serializationModel="Studio.02.02.00">
	<object class="AudioFile" id="{607c2f3d-5d47-482d-bd26-ea85c3171ad9}">
		<property name="assetPath">
			<value>HadesField_0356.ogg</value>
		</property>
		<property name="frequencyInKHz">
			<value>32</value>
		</property>
		<property name="channelCount">
			<value>2</value>
		</property>
		<property name="length">
			<value>4.766</value>
		</property>
		<relationship name="masterAssetFolder">
			<destination>{bb31ee21-3abf-4df1-9c43-d5c3e0a3a024}</destination>
		</relationship>
	</object>
</objects>
