{"name": "bin\\Win\\Atlases\\ModsNikkelMHadesBiomesFxOriginal29", "version": 4, "subAtlases": [{"name": "Fx\\TartarusGhostHandsMulti\\TartarusGhostHandsMulti0040", "topLeft": {"x": 23, "y": 20}, "originalSize": {"x": 250, "y": 250}, "rect": {"x": 0, "y": 0, "width": 227, "height": 228}, "scaleRatio": {"x": 1.0, "y": 1.0}, "isMulti": false, "isMip": false, "isAlpha8": false, "hull": []}, {"name": "Fx\\TartarusGhostHandsMulti\\TartarusGhostHandsMulti0041", "topLeft": {"x": 23, "y": 20}, "originalSize": {"x": 250, "y": 250}, "rect": {"x": 0, "y": 228, "width": 227, "height": 228}, "scaleRatio": {"x": 1.0, "y": 1.0}, "isMulti": false, "isMip": false, "isAlpha8": false, "hull": []}, {"name": "Fx\\TartarusGhostHandsMulti\\TartarusGhostHandsMulti0042", "topLeft": {"x": 23, "y": 20}, "originalSize": {"x": 250, "y": 250}, "rect": {"x": 0, "y": 456, "width": 227, "height": 228}, "scaleRatio": {"x": 1.0, "y": 1.0}, "isMulti": false, "isMip": false, "isAlpha8": false, "hull": []}, {"name": "Fx\\TartarusGhostHandsMulti\\TartarusGhostHandsMulti0043", "topLeft": {"x": 23, "y": 20}, "originalSize": {"x": 250, "y": 250}, "rect": {"x": 0, "y": 684, "width": 227, "height": 228}, "scaleRatio": {"x": 1.0, "y": 1.0}, "isMulti": false, "isMip": false, "isAlpha8": false, "hull": []}, {"name": "Fx\\TartarusGhostHandsMulti\\TartarusGhostHandsMulti0044", "topLeft": {"x": 22, "y": 20}, "originalSize": {"x": 250, "y": 250}, "rect": {"x": 0, "y": 912, "width": 228, "height": 228}, "scaleRatio": {"x": 1.0, "y": 1.0}, "isMulti": false, "isMip": false, "isAlpha8": false, "hull": []}, {"name": "Fx\\TartarusGhostHandsMulti\\TartarusGhostHandsMulti0076", "topLeft": {"x": 15, "y": 12}, "originalSize": {"x": 250, "y": 250}, "rect": {"x": 227, "y": 0, "width": 227, "height": 228}, "scaleRatio": {"x": 1.0, "y": 1.0}, "isMulti": false, "isMip": false, "isAlpha8": false, "hull": []}, {"name": "Fx\\TartarusGhostHandsMulti\\TartarusGhostHandsMulti0077", "topLeft": {"x": 14, "y": 12}, "originalSize": {"x": 250, "y": 250}, "rect": {"x": 227, "y": 228, "width": 228, "height": 228}, "scaleRatio": {"x": 1.0, "y": 1.0}, "isMulti": false, "isMip": false, "isAlpha8": false, "hull": []}, {"name": "Fx\\TartarusGhostHandsMulti\\TartarusGhostHandsMulti0078", "topLeft": {"x": 14, "y": 12}, "originalSize": {"x": 250, "y": 250}, "rect": {"x": 454, "y": 0, "width": 227, "height": 228}, "scaleRatio": {"x": 1.0, "y": 1.0}, "isMulti": false, "isMip": false, "isAlpha8": false, "hull": []}, {"name": "Fx\\TartarusGhostHandsMulti\\TartarusGhostHandsMulti0079", "topLeft": {"x": 13, "y": 12}, "originalSize": {"x": 250, "y": 250}, "rect": {"x": 227, "y": 456, "width": 226, "height": 228}, "scaleRatio": {"x": 1.0, "y": 1.0}, "isMulti": false, "isMip": false, "isAlpha8": false, "hull": []}, {"name": "Fx\\TartarusGhostHandsMulti\\TartarusGhostHandsMulti0080", "topLeft": {"x": 13, "y": 12}, "originalSize": {"x": 250, "y": 250}, "rect": {"x": 227, "y": 684, "width": 225, "height": 228}, "scaleRatio": {"x": 1.0, "y": 1.0}, "isMulti": false, "isMip": false, "isAlpha8": false, "hull": []}, {"name": "Fx\\TartarusGhostHandsMulti\\TartarusGhostHandsMulti0081", "topLeft": {"x": 13, "y": 12}, "originalSize": {"x": 250, "y": 250}, "rect": {"x": 0, "y": 1140, "width": 225, "height": 228}, "scaleRatio": {"x": 1.0, "y": 1.0}, "isMulti": false, "isMip": false, "isAlpha8": false, "hull": []}, {"name": "Fx\\TartarusGhostHandsMulti\\TartarusGhostHandsMulti0082", "topLeft": {"x": 13, "y": 12}, "originalSize": {"x": 250, "y": 250}, "rect": {"x": 0, "y": 1368, "width": 224, "height": 228}, "scaleRatio": {"x": 1.0, "y": 1.0}, "isMulti": false, "isMip": false, "isAlpha8": false, "hull": []}, {"name": "Fx\\Elysium_Urn_01_ShatterB\\Elysium_Urn_01_ShatterB0011", "topLeft": {"x": 0, "y": 64}, "originalSize": {"x": 240, "y": 280}, "rect": {"x": 0, "y": 1596, "width": 227, "height": 176}, "scaleRatio": {"x": 1.0, "y": 1.0}, "isMulti": false, "isMip": false, "isAlpha8": false, "hull": []}, {"name": "Fx\\HadesBidentArc\\HadesBidentArc0013", "topLeft": {"x": 94, "y": 140}, "originalSize": {"x": 634, "y": 634}, "rect": {"x": 224, "y": 1368, "width": 163, "height": 227}, "scaleRatio": {"x": 1.0, "y": 1.0}, "isMulti": false, "isMip": false, "isAlpha8": false, "hull": []}, {"name": "Fx\\MainMenuZagHair\\MainMenuZagHair0004", "topLeft": {"x": 38, "y": 36}, "originalSize": {"x": 360, "y": 400}, "rect": {"x": 225, "y": 1140, "width": 227, "height": 205}, "scaleRatio": {"x": 1.0, "y": 1.0}, "isMulti": false, "isMip": false, "isAlpha8": false, "hull": []}, {"name": "Fx\\MainMenuZagHair\\MainMenuZagHair0005", "topLeft": {"x": 38, "y": 36}, "originalSize": {"x": 360, "y": 400}, "rect": {"x": 228, "y": 912, "width": 227, "height": 205}, "scaleRatio": {"x": 1.0, "y": 1.0}, "isMulti": false, "isMip": false, "isAlpha8": false, "hull": []}, {"name": "Fx\\MainMenuZagHair\\MainMenuZagHair0006", "topLeft": {"x": 38, "y": 35}, "originalSize": {"x": 360, "y": 400}, "rect": {"x": 452, "y": 684, "width": 227, "height": 206}, "scaleRatio": {"x": 1.0, "y": 1.0}, "isMulti": false, "isMip": false, "isAlpha8": false, "hull": []}, {"name": "Fx\\MainMenuZagHair\\MainMenuZagHair0007", "topLeft": {"x": 38, "y": 35}, "originalSize": {"x": 360, "y": 400}, "rect": {"x": 453, "y": 456, "width": 227, "height": 206}, "scaleRatio": {"x": 1.0, "y": 1.0}, "isMulti": false, "isMip": false, "isAlpha8": false, "hull": []}, {"name": "Fx\\MainMenuZagHair\\MainMenuZagHair0008", "topLeft": {"x": 38, "y": 35}, "originalSize": {"x": 360, "y": 400}, "rect": {"x": 455, "y": 228, "width": 227, "height": 206}, "scaleRatio": {"x": 1.0, "y": 1.0}, "isMulti": false, "isMip": false, "isAlpha8": false, "hull": []}, {"name": "Fx\\MainMenuZagHair\\MainMenuZagHair0009", "topLeft": {"x": 38, "y": 35}, "originalSize": {"x": 360, "y": 400}, "rect": {"x": 681, "y": 0, "width": 227, "height": 206}, "scaleRatio": {"x": 1.0, "y": 1.0}, "isMulti": false, "isMip": false, "isAlpha8": false, "hull": []}, {"name": "Fx\\MainMenuZagHair\\MainMenuZagHair0010", "topLeft": {"x": 38, "y": 35}, "originalSize": {"x": 360, "y": 400}, "rect": {"x": 0, "y": 1772, "width": 227, "height": 206}, "scaleRatio": {"x": 1.0, "y": 1.0}, "isMulti": false, "isMip": false, "isAlpha8": false, "hull": []}, {"name": "Fx\\MainMenuZagHair\\MainMenuZagHair0011", "topLeft": {"x": 38, "y": 35}, "originalSize": {"x": 360, "y": 400}, "rect": {"x": 0, "y": 1978, "width": 227, "height": 206}, "scaleRatio": {"x": 1.0, "y": 1.0}, "isMulti": false, "isMip": false, "isAlpha8": false, "hull": []}, {"name": "Fx\\MainMenuZagHair\\MainMenuZagHair0012", "topLeft": {"x": 38, "y": 35}, "originalSize": {"x": 360, "y": 400}, "rect": {"x": 0, "y": 2184, "width": 227, "height": 206}, "scaleRatio": {"x": 1.0, "y": 1.0}, "isMulti": false, "isMip": false, "isAlpha8": false, "hull": []}, {"name": "Fx\\MainMenuZagHair\\MainMenuZagHair0013", "topLeft": {"x": 38, "y": 35}, "originalSize": {"x": 360, "y": 400}, "rect": {"x": 0, "y": 2390, "width": 227, "height": 206}, "scaleRatio": {"x": 1.0, "y": 1.0}, "isMulti": false, "isMip": false, "isAlpha8": false, "hull": []}, {"name": "Fx\\MainMenuZagHair\\MainMenuZagHair0014", "topLeft": {"x": 38, "y": 35}, "originalSize": {"x": 360, "y": 400}, "rect": {"x": 0, "y": 2596, "width": 227, "height": 206}, "scaleRatio": {"x": 1.0, "y": 1.0}, "isMulti": false, "isMip": false, "isAlpha8": false, "hull": []}, {"name": "Fx\\MainMenuZagHair\\MainMenuZagHair0057", "topLeft": {"x": 38, "y": 36}, "originalSize": {"x": 360, "y": 400}, "rect": {"x": 227, "y": 2596, "width": 227, "height": 205}, "scaleRatio": {"x": 1.0, "y": 1.0}, "isMulti": false, "isMip": false, "isAlpha8": false, "hull": []}, {"name": "Fx\\MainMenuZagHair\\MainMenuZagHair0080", "topLeft": {"x": 39, "y": 36}, "originalSize": {"x": 360, "y": 400}, "rect": {"x": 227, "y": 1595, "width": 227, "height": 205}, "scaleRatio": {"x": 1.0, "y": 1.0}, "isMulti": false, "isMip": false, "isAlpha8": false, "hull": []}, {"name": "Fx\\ProjectileFireRing\\ProjectileFireRing0402", "topLeft": {"x": 95, "y": 88}, "originalSize": {"x": 320, "y": 320}, "rect": {"x": 387, "y": 1345, "width": 218, "height": 227}, "scaleRatio": {"x": 1.0, "y": 1.0}, "isMulti": false, "isMip": false, "isAlpha8": false, "hull": []}, {"name": "Fx\\Shielded\\Shielded0022", "topLeft": {"x": 4, "y": 46}, "originalSize": {"x": 256, "y": 256}, "rect": {"x": 452, "y": 1117, "width": 227, "height": 166}, "scaleRatio": {"x": 1.0, "y": 1.0}, "isMulti": false, "isMip": false, "isAlpha8": false, "hull": []}, {"name": "Fx\\Shielded\\Shielded0023", "topLeft": {"x": 11, "y": 46}, "originalSize": {"x": 256, "y": 256}, "rect": {"x": 455, "y": 890, "width": 227, "height": 166}, "scaleRatio": {"x": 1.0, "y": 1.0}, "isMulti": false, "isMip": false, "isAlpha8": false, "hull": []}, {"name": "Fx\\ShrineDoorOpen\\ShrineDoorOpen0021", "topLeft": {"x": 26, "y": 17}, "originalSize": {"x": 250, "y": 350}, "rect": {"x": 679, "y": 662, "width": 199, "height": 227}, "scaleRatio": {"x": 1.0, "y": 1.0}, "isMulti": false, "isMip": false, "isAlpha8": false, "hull": []}, {"name": "Fx\\ShrineDoorOpen\\ShrineDoorOpen0035", "topLeft": {"x": 22, "y": 23}, "originalSize": {"x": 250, "y": 350}, "rect": {"x": 680, "y": 434, "width": 207, "height": 227}, "scaleRatio": {"x": 1.0, "y": 1.0}, "isMulti": false, "isMip": false, "isAlpha8": false, "hull": []}, {"name": "Fx\\TartarusGhostHands\\TartarusGhostHands0079", "topLeft": {"x": 21, "y": 41}, "originalSize": {"x": 250, "y": 250}, "rect": {"x": 682, "y": 206, "width": 227, "height": 136}, "scaleRatio": {"x": 1.0, "y": 1.0}, "isMulti": false, "isMip": false, "isAlpha8": false, "hull": []}, {"name": "Fx\\TartarusGhostHands\\TartarusGhostHands0080", "topLeft": {"x": 21, "y": 41}, "originalSize": {"x": 250, "y": 250}, "rect": {"x": 908, "y": 0, "width": 227, "height": 136}, "scaleRatio": {"x": 1.0, "y": 1.0}, "isMulti": false, "isMip": false, "isAlpha8": false, "hull": []}, {"name": "Fx\\TartarusGhostHandsMulti\\TartarusGhostHandsMulti0039", "topLeft": {"x": 24, "y": 21}, "originalSize": {"x": 250, "y": 250}, "rect": {"x": 227, "y": 1800, "width": 226, "height": 227}, "scaleRatio": {"x": 1.0, "y": 1.0}, "isMulti": false, "isMip": false, "isAlpha8": false, "hull": []}, {"name": "Fx\\TartarusGhostHandsMulti\\TartarusGhostHandsMulti0088", "topLeft": {"x": 14, "y": 13}, "originalSize": {"x": 250, "y": 250}, "rect": {"x": 227, "y": 2027, "width": 217, "height": 227}, "scaleRatio": {"x": 1.0, "y": 1.0}, "isMulti": false, "isMip": false, "isAlpha8": false, "hull": []}, {"name": "Fx\\TartarusGhostHandsMulti\\TartarusGhostHandsMulti0090", "topLeft": {"x": 15, "y": 13}, "originalSize": {"x": 250, "y": 250}, "rect": {"x": 227, "y": 2254, "width": 216, "height": 227}, "scaleRatio": {"x": 1.0, "y": 1.0}, "isMulti": false, "isMip": false, "isAlpha8": false, "hull": []}, {"name": "Fx\\EurydiceShield\\EurydiceShield0022", "topLeft": {"x": 54, "y": 69}, "originalSize": {"x": 333, "y": 333}, "rect": {"x": 443, "y": 2254, "width": 226, "height": 189}, "scaleRatio": {"x": 1.0, "y": 1.0}, "isMulti": false, "isMip": false, "isAlpha8": false, "hull": []}, {"name": "Fx\\MainMenuBloodstone\\MainMenuBloodstone0044", "topLeft": {"x": 29, "y": 162}, "originalSize": {"x": 300, "y": 400}, "rect": {"x": 444, "y": 2027, "width": 226, "height": 167}, "scaleRatio": {"x": 1.0, "y": 1.0}, "isMulti": false, "isMip": false, "isAlpha8": false, "hull": []}, {"name": "Fx\\MainMenuZagHair\\MainMenuZagHair0001", "topLeft": {"x": 39, "y": 36}, "originalSize": {"x": 360, "y": 400}, "rect": {"x": 453, "y": 1800, "width": 226, "height": 205}, "scaleRatio": {"x": 1.0, "y": 1.0}, "isMulti": false, "isMip": false, "isAlpha8": false, "hull": []}, {"name": "Fx\\MainMenuZagHair\\MainMenuZagHair0002", "topLeft": {"x": 39, "y": 36}, "originalSize": {"x": 360, "y": 400}, "rect": {"x": 454, "y": 1572, "width": 226, "height": 205}, "scaleRatio": {"x": 1.0, "y": 1.0}, "isMulti": false, "isMip": false, "isAlpha8": false, "hull": []}, {"name": "Fx\\MainMenuZagHair\\MainMenuZagHair0003", "topLeft": {"x": 39, "y": 36}, "originalSize": {"x": 360, "y": 400}, "rect": {"x": 605, "y": 1283, "width": 226, "height": 205}, "scaleRatio": {"x": 1.0, "y": 1.0}, "isMulti": false, "isMip": false, "isAlpha8": false, "hull": []}, {"name": "Fx\\MainMenuZagHair\\MainMenuZagHair0015", "topLeft": {"x": 39, "y": 35}, "originalSize": {"x": 360, "y": 400}, "rect": {"x": 679, "y": 1056, "width": 226, "height": 206}, "scaleRatio": {"x": 1.0, "y": 1.0}, "isMulti": false, "isMip": false, "isAlpha8": false, "hull": []}, {"name": "Fx\\MainMenuZagHair\\MainMenuZagHair0016", "topLeft": {"x": 39, "y": 36}, "originalSize": {"x": 360, "y": 400}, "rect": {"x": 878, "y": 661, "width": 226, "height": 205}, "scaleRatio": {"x": 1.0, "y": 1.0}, "isMulti": false, "isMip": false, "isAlpha8": false, "hull": []}, {"name": "Fx\\MainMenuZagHair\\MainMenuZagHair0017", "topLeft": {"x": 39, "y": 36}, "originalSize": {"x": 360, "y": 400}, "rect": {"x": 887, "y": 342, "width": 226, "height": 205}, "scaleRatio": {"x": 1.0, "y": 1.0}, "isMulti": false, "isMip": false, "isAlpha8": false, "hull": []}, {"name": "Fx\\MainMenuZagHair\\MainMenuZagHair0018", "topLeft": {"x": 39, "y": 36}, "originalSize": {"x": 360, "y": 400}, "rect": {"x": 909, "y": 136, "width": 226, "height": 205}, "scaleRatio": {"x": 1.0, "y": 1.0}, "isMulti": false, "isMip": false, "isAlpha8": false, "hull": []}, {"name": "Fx\\MainMenuZagHair\\MainMenuZagHair0041", "topLeft": {"x": 39, "y": 36}, "originalSize": {"x": 360, "y": 400}, "rect": {"x": 454, "y": 2443, "width": 226, "height": 205}, "scaleRatio": {"x": 1.0, "y": 1.0}, "isMulti": false, "isMip": false, "isAlpha8": false, "hull": []}, {"name": "Fx\\MainMenuZagHair\\MainMenuZagHair0042", "topLeft": {"x": 39, "y": 36}, "originalSize": {"x": 360, "y": 400}, "rect": {"x": 454, "y": 2648, "width": 226, "height": 205}, "scaleRatio": {"x": 1.0, "y": 1.0}, "isMulti": false, "isMip": false, "isAlpha8": false, "hull": []}, {"name": "Fx\\MainMenuZagHair\\MainMenuZagHair0043", "topLeft": {"x": 39, "y": 36}, "originalSize": {"x": 360, "y": 400}, "rect": {"x": 680, "y": 2648, "width": 226, "height": 205}, "scaleRatio": {"x": 1.0, "y": 1.0}, "isMulti": false, "isMip": false, "isAlpha8": false, "hull": []}, {"name": "Fx\\MainMenuZagHair\\MainMenuZagHair0044", "topLeft": {"x": 39, "y": 36}, "originalSize": {"x": 360, "y": 400}, "rect": {"x": 669, "y": 2194, "width": 226, "height": 205}, "scaleRatio": {"x": 1.0, "y": 1.0}, "isMulti": false, "isMip": false, "isAlpha8": false, "hull": []}, {"name": "Fx\\MainMenuZagHair\\MainMenuZagHair0045", "topLeft": {"x": 39, "y": 35}, "originalSize": {"x": 360, "y": 400}, "rect": {"x": 680, "y": 2399, "width": 226, "height": 206}, "scaleRatio": {"x": 1.0, "y": 1.0}, "isMulti": false, "isMip": false, "isAlpha8": false, "hull": []}, {"name": "Fx\\MainMenuZagHair\\MainMenuZagHair0046", "topLeft": {"x": 39, "y": 35}, "originalSize": {"x": 360, "y": 400}, "rect": {"x": 679, "y": 1777, "width": 226, "height": 206}, "scaleRatio": {"x": 1.0, "y": 1.0}, "isMulti": false, "isMip": false, "isAlpha8": false, "hull": []}, {"name": "Fx\\MainMenuZagHair\\MainMenuZagHair0047", "topLeft": {"x": 39, "y": 35}, "originalSize": {"x": 360, "y": 400}, "rect": {"x": 679, "y": 1983, "width": 226, "height": 206}, "scaleRatio": {"x": 1.0, "y": 1.0}, "isMulti": false, "isMip": false, "isAlpha8": false, "hull": []}, {"name": "Fx\\MainMenuZagHair\\MainMenuZagHair0048", "topLeft": {"x": 39, "y": 35}, "originalSize": {"x": 360, "y": 400}, "rect": {"x": 895, "y": 2189, "width": 226, "height": 206}, "scaleRatio": {"x": 1.0, "y": 1.0}, "isMulti": false, "isMip": false, "isAlpha8": false, "hull": []}, {"name": "Fx\\MainMenuZagHair\\MainMenuZagHair0049", "topLeft": {"x": 39, "y": 35}, "originalSize": {"x": 360, "y": 400}, "rect": {"x": 680, "y": 1488, "width": 226, "height": 206}, "scaleRatio": {"x": 1.0, "y": 1.0}, "isMulti": false, "isMip": false, "isAlpha8": false, "hull": []}, {"name": "Fx\\MainMenuZagHair\\MainMenuZagHair0050", "topLeft": {"x": 39, "y": 35}, "originalSize": {"x": 360, "y": 400}, "rect": {"x": 831, "y": 1262, "width": 226, "height": 206}, "scaleRatio": {"x": 1.0, "y": 1.0}, "isMulti": false, "isMip": false, "isAlpha8": false, "hull": []}, {"name": "Fx\\MainMenuZagHair\\MainMenuZagHair0051", "topLeft": {"x": 39, "y": 35}, "originalSize": {"x": 360, "y": 400}, "rect": {"x": 905, "y": 866, "width": 226, "height": 206}, "scaleRatio": {"x": 1.0, "y": 1.0}, "isMulti": false, "isMip": false, "isAlpha8": false, "hull": []}, {"name": "Fx\\MainMenuZagHair\\MainMenuZagHair0052", "topLeft": {"x": 39, "y": 35}, "originalSize": {"x": 360, "y": 400}, "rect": {"x": 1104, "y": 547, "width": 226, "height": 206}, "scaleRatio": {"x": 1.0, "y": 1.0}, "isMulti": false, "isMip": false, "isAlpha8": false, "hull": []}, {"name": "Fx\\MainMenuZagHair\\MainMenuZagHair0053", "topLeft": {"x": 39, "y": 35}, "originalSize": {"x": 360, "y": 400}, "rect": {"x": 1113, "y": 341, "width": 226, "height": 206}, "scaleRatio": {"x": 1.0, "y": 1.0}, "isMulti": false, "isMip": false, "isAlpha8": false, "hull": []}, {"name": "Fx\\MainMenuZagHair\\MainMenuZagHair0054", "topLeft": {"x": 39, "y": 35}, "originalSize": {"x": 360, "y": 400}, "rect": {"x": 1135, "y": 0, "width": 226, "height": 206}, "scaleRatio": {"x": 1.0, "y": 1.0}, "isMulti": false, "isMip": false, "isAlpha8": false, "hull": []}, {"name": "Fx\\MainMenuZagHair\\MainMenuZagHair0055", "topLeft": {"x": 39, "y": 35}, "originalSize": {"x": 360, "y": 400}, "rect": {"x": 906, "y": 2395, "width": 226, "height": 206}, "scaleRatio": {"x": 1.0, "y": 1.0}, "isMulti": false, "isMip": false, "isAlpha8": false, "hull": []}, {"name": "Fx\\MainMenuZagHair\\MainMenuZagHair0056", "topLeft": {"x": 39, "y": 36}, "originalSize": {"x": 360, "y": 400}, "rect": {"x": 906, "y": 2601, "width": 226, "height": 205}, "scaleRatio": {"x": 1.0, "y": 1.0}, "isMulti": false, "isMip": false, "isAlpha8": false, "hull": []}, {"name": "Fx\\ProjectileFireRing\\ProjectileFireRing0164", "topLeft": {"x": 23, "y": 19}, "originalSize": {"x": 320, "y": 320}, "rect": {"x": 1132, "y": 2601, "width": 226, "height": 191}, "scaleRatio": {"x": 1.0, "y": 1.0}, "isMulti": false, "isMip": false, "isAlpha8": false, "hull": []}, {"name": "Fx\\ProjectileFireRing\\ProjectileFireRing0165", "topLeft": {"x": 23, "y": 18}, "originalSize": {"x": 320, "y": 320}, "rect": {"x": 905, "y": 1694, "width": 226, "height": 195}, "scaleRatio": {"x": 1.0, "y": 1.0}, "isMulti": false, "isMip": false, "isAlpha8": false, "hull": []}, {"name": "Fx\\ProjectileFireRing\\ProjectileFireRing0228", "topLeft": {"x": 28, "y": 28}, "originalSize": {"x": 320, "y": 320}, "rect": {"x": 906, "y": 1468, "width": 130, "height": 226}, "scaleRatio": {"x": 1.0, "y": 1.0}, "isMulti": false, "isMip": false, "isAlpha8": false, "hull": []}, {"name": "Fx\\ProjectileFireRing\\ProjectileFireRing0232", "topLeft": {"x": 46, "y": 29}, "originalSize": {"x": 320, "y": 320}, "rect": {"x": 1036, "y": 1468, "width": 119, "height": 226}, "scaleRatio": {"x": 1.0, "y": 1.0}, "isMulti": false, "isMip": false, "isAlpha8": false, "hull": []}, {"name": "Fx\\ProjectileFireRing\\ProjectileFireRing0315", "topLeft": {"x": 4, "y": 80}, "originalSize": {"x": 320, "y": 320}, "rect": {"x": 905, "y": 1889, "width": 186, "height": 226}, "scaleRatio": {"x": 1.0, "y": 1.0}, "isMulti": false, "isMip": false, "isAlpha8": false, "hull": []}, {"name": "Fx\\ProjectileFireRing\\ProjectileFireRing0352", "topLeft": {"x": 11, "y": 89}, "originalSize": {"x": 320, "y": 320}, "rect": {"x": 1091, "y": 1889, "width": 226, "height": 220}, "scaleRatio": {"x": 1.0, "y": 1.0}, "isMulti": false, "isMip": false, "isAlpha8": false, "hull": []}, {"name": "Fx\\ProjectileFireRing\\ProjectileFireRing0384", "topLeft": {"x": 47, "y": 101}, "originalSize": {"x": 320, "y": 320}, "rect": {"x": 1131, "y": 1694, "width": 226, "height": 195}, "scaleRatio": {"x": 1.0, "y": 1.0}, "isMulti": false, "isMip": false, "isAlpha8": false, "hull": []}, {"name": "Fx\\ProjectileFireRing\\ProjectileFireRing0401", "topLeft": {"x": 101, "y": 88}, "originalSize": {"x": 320, "y": 320}, "rect": {"x": 1121, "y": 2109, "width": 211, "height": 226}, "scaleRatio": {"x": 1.0, "y": 1.0}, "isMulti": false, "isMip": false, "isAlpha8": false, "hull": []}, {"name": "Fx\\ShadeTrail\\ShadeTrail0005", "topLeft": {"x": 134, "y": 82}, "originalSize": {"x": 333, "y": 333}, "rect": {"x": 1132, "y": 2335, "width": 158, "height": 226}, "scaleRatio": {"x": 1.0, "y": 1.0}, "isMulti": false, "isMip": false, "isAlpha8": false, "hull": []}, {"name": "Fx\\Shielded\\Shielded0003", "topLeft": {"x": 5, "y": 45}, "originalSize": {"x": 256, "y": 256}, "rect": {"x": 905, "y": 1072, "width": 226, "height": 168}, "scaleRatio": {"x": 1.0, "y": 1.0}, "isMulti": false, "isMip": false, "isAlpha8": false, "hull": []}, {"name": "Fx\\Shielded\\Shielded0019", "topLeft": {"x": 8, "y": 45}, "originalSize": {"x": 256, "y": 256}, "rect": {"x": 1317, "y": 1889, "width": 226, "height": 167}, "scaleRatio": {"x": 1.0, "y": 1.0}, "isMulti": false, "isMip": false, "isAlpha8": false, "hull": []}, {"name": "Fx\\ShieldEmpowerBack\\ShieldEmpowerBack0005", "topLeft": {"x": 54, "y": 64}, "originalSize": {"x": 320, "y": 240}, "rect": {"x": 0, "y": 2802, "width": 226, "height": 77}, "scaleRatio": {"x": 1.0, "y": 1.0}, "isMulti": false, "isMip": false, "isAlpha8": false, "hull": []}, {"name": "Fx\\ShieldEmpowerBack\\ShieldEmpowerBack0006", "topLeft": {"x": 54, "y": 64}, "originalSize": {"x": 320, "y": 240}, "rect": {"x": 226, "y": 2802, "width": 226, "height": 77}, "scaleRatio": {"x": 1.0, "y": 1.0}, "isMulti": false, "isMip": false, "isAlpha8": false, "hull": []}, {"name": "Fx\\ShieldEmpowerBack\\ShieldEmpowerBack0012", "topLeft": {"x": 41, "y": 61}, "originalSize": {"x": 320, "y": 240}, "rect": {"x": 1132, "y": 2792, "width": 226, "height": 81}, "scaleRatio": {"x": 1.0, "y": 1.0}, "isMulti": false, "isMip": false, "isAlpha8": false, "hull": []}, {"name": "Fx\\ShieldEmpowerFront\\ShieldEmpowerFront0006", "topLeft": {"x": 54, "y": 115}, "originalSize": {"x": 320, "y": 240}, "rect": {"x": 1358, "y": 2792, "width": 226, "height": 82}, "scaleRatio": {"x": 1.0, "y": 1.0}, "isMulti": false, "isMip": false, "isAlpha8": false, "hull": []}, {"name": "Fx\\ShrineDoorLoop\\ShrineDoorLoop0035", "topLeft": {"x": 22, "y": 24}, "originalSize": {"x": 250, "y": 350}, "rect": {"x": 1057, "y": 1240, "width": 207, "height": 226}, "scaleRatio": {"x": 1.0, "y": 1.0}, "isMulti": false, "isMip": false, "isAlpha8": false, "hull": []}, {"name": "Fx\\ShrineDoorOpen\\ShrineDoorOpen0020", "topLeft": {"x": 25, "y": 19}, "originalSize": {"x": 250, "y": 350}, "rect": {"x": 1155, "y": 1466, "width": 199, "height": 226}, "scaleRatio": {"x": 1.0, "y": 1.0}, "isMulti": false, "isMip": false, "isAlpha8": false, "hull": []}, {"name": "Fx\\TartarusGhostHands\\TartarusGhostHands0026", "topLeft": {"x": 18, "y": 32}, "originalSize": {"x": 250, "y": 250}, "rect": {"x": 1135, "y": 206, "width": 226, "height": 134}, "scaleRatio": {"x": 1.0, "y": 1.0}, "isMulti": false, "isMip": false, "isAlpha8": false, "hull": []}, {"name": "Fx\\TartarusGhostHands\\TartarusGhostHands0027", "topLeft": {"x": 18, "y": 32}, "originalSize": {"x": 250, "y": 250}, "rect": {"x": 1290, "y": 2335, "width": 226, "height": 134}, "scaleRatio": {"x": 1.0, "y": 1.0}, "isMulti": false, "isMip": false, "isAlpha8": false, "hull": []}, {"name": "Fx\\TartarusGhostHands\\TartarusGhostHands0028", "topLeft": {"x": 18, "y": 31}, "originalSize": {"x": 250, "y": 250}, "rect": {"x": 1332, "y": 2056, "width": 226, "height": 135}, "scaleRatio": {"x": 1.0, "y": 1.0}, "isMulti": false, "isMip": false, "isAlpha8": false, "hull": []}, {"name": "Fx\\TartarusGhostHands\\TartarusGhostHands0081", "topLeft": {"x": 21, "y": 41}, "originalSize": {"x": 250, "y": 250}, "rect": {"x": 1332, "y": 2191, "width": 226, "height": 137}, "scaleRatio": {"x": 1.0, "y": 1.0}, "isMulti": false, "isMip": false, "isAlpha8": false, "hull": []}, {"name": "Fx\\TartarusGhostHandsMulti\\TartarusGhostHandsMulti0038", "topLeft": {"x": 24, "y": 21}, "originalSize": {"x": 250, "y": 250}, "rect": {"x": 1358, "y": 2469, "width": 225, "height": 226}, "scaleRatio": {"x": 1.0, "y": 1.0}, "isMulti": false, "isMip": false, "isAlpha8": false, "hull": []}, {"name": "Fx\\TartarusGhostHandsMulti\\TartarusGhostHandsMulti0089", "topLeft": {"x": 15, "y": 13}, "originalSize": {"x": 250, "y": 250}, "rect": {"x": 1131, "y": 753, "width": 216, "height": 226}, "scaleRatio": {"x": 1.0, "y": 1.0}, "isMulti": false, "isMip": false, "isAlpha8": false, "hull": []}, {"name": "Fx\\WarpGateLoop\\WarpGateLoop0032", "topLeft": {"x": 31, "y": 15}, "originalSize": {"x": 200, "y": 270}, "rect": {"x": 1131, "y": 979, "width": 143, "height": 226}, "scaleRatio": {"x": 1.0, "y": 1.0}, "isMulti": false, "isMip": false, "isAlpha8": false, "hull": []}, {"name": "Fx\\WarpGateLoop\\WarpGateLoop0050", "topLeft": {"x": 27, "y": 19}, "originalSize": {"x": 200, "y": 270}, "rect": {"x": 1264, "y": 1205, "width": 148, "height": 226}, "scaleRatio": {"x": 1.0, "y": 1.0}, "isMulti": false, "isMip": false, "isAlpha8": false, "hull": []}, {"name": "Fx\\ProjectileFireRing\\ProjectileFireRing0133", "topLeft": {"x": 50, "y": 17}, "originalSize": {"x": 320, "y": 320}, "rect": {"x": 1330, "y": 547, "width": 225, "height": 188}, "scaleRatio": {"x": 1.0, "y": 1.0}, "isMulti": false, "isMip": false, "isAlpha8": false, "hull": []}, {"name": "Fx\\ProjectileFireRing\\ProjectileFireRing0227", "topLeft": {"x": 24, "y": 28}, "originalSize": {"x": 320, "y": 320}, "rect": {"x": 1274, "y": 979, "width": 131, "height": 225}, "scaleRatio": {"x": 1.0, "y": 1.0}, "isMulti": false, "isMip": false, "isAlpha8": false, "hull": []}, {"name": "Fx\\ProjectileFireRing\\ProjectileFireRing0314", "topLeft": {"x": 3, "y": 80}, "originalSize": {"x": 320, "y": 320}, "rect": {"x": 1347, "y": 735, "width": 187, "height": 225}, "scaleRatio": {"x": 1.0, "y": 1.0}, "isMulti": false, "isMip": false, "isAlpha8": false, "hull": []}, {"name": "Fx\\ProjectileFireRing\\ProjectileFireRing0340", "topLeft": {"x": 10, "y": 91}, "originalSize": {"x": 320, "y": 320}, "rect": {"x": 1405, "y": 960, "width": 225, "height": 222}, "scaleRatio": {"x": 1.0, "y": 1.0}, "isMulti": false, "isMip": false, "isAlpha8": false, "hull": []}, {"name": "Fx\\ProjectileFireRing\\ProjectileFireRing0353", "topLeft": {"x": 13, "y": 88}, "originalSize": {"x": 320, "y": 320}, "rect": {"x": 1534, "y": 735, "width": 225, "height": 216}, "scaleRatio": {"x": 1.0, "y": 1.0}, "isMulti": false, "isMip": false, "isAlpha8": false, "hull": []}, {"name": "Fx\\ShadeSwordSwipeOverHead\\ShadeSwordSwipeOverHead0003", "topLeft": {"x": 183, "y": 4}, "originalSize": {"x": 400, "y": 400}, "rect": {"x": 1354, "y": 1431, "width": 214, "height": 225}, "scaleRatio": {"x": 1.0, "y": 1.0}, "isMulti": false, "isMip": false, "isAlpha8": false, "hull": []}, {"name": "Fx\\Shielded\\Shielded0050", "topLeft": {"x": 19, "y": 48}, "originalSize": {"x": 256, "y": 256}, "rect": {"x": 1339, "y": 340, "width": 225, "height": 163}, "scaleRatio": {"x": 1.0, "y": 1.0}, "isMulti": false, "isMip": false, "isAlpha8": false, "hull": []}, {"name": "Fx\\ShrineDoorLoop\\ShrineDoorLoop0005", "topLeft": {"x": 20, "y": 27}, "originalSize": {"x": 250, "y": 350}, "rect": {"x": 1555, "y": 503, "width": 211, "height": 225}, "scaleRatio": {"x": 1.0, "y": 1.0}, "isMulti": false, "isMip": false, "isAlpha8": false, "hull": []}, {"name": "Fx\\ShrineDoorLoop\\ShrineDoorLoop0045", "topLeft": {"x": 19, "y": 27}, "originalSize": {"x": 250, "y": 350}, "rect": {"x": 1357, "y": 1656, "width": 212, "height": 225}, "scaleRatio": {"x": 1.0, "y": 1.0}, "isMulti": false, "isMip": false, "isAlpha8": false, "hull": []}, {"name": "Fx\\ShrineDoorOpen\\ShrineDoorOpen0019", "topLeft": {"x": 25, "y": 21}, "originalSize": {"x": 250, "y": 350}, "rect": {"x": 1412, "y": 1182, "width": 200, "height": 225}, "scaleRatio": {"x": 1.0, "y": 1.0}, "isMulti": false, "isMip": false, "isAlpha8": false, "hull": []}, {"name": "Fx\\SnowSparseClean\\SnowSparseClean0004", "topLeft": {"x": 61, "y": 61}, "originalSize": {"x": 320, "y": 320}, "rect": {"x": 1568, "y": 1407, "width": 202, "height": 225}, "scaleRatio": {"x": 1.0, "y": 1.0}, "isMulti": false, "isMip": false, "isAlpha8": false, "hull": []}, {"name": "Fx\\TartarusGhostHands\\TartarusGhostHands0025", "topLeft": {"x": 18, "y": 33}, "originalSize": {"x": 250, "y": 250}, "rect": {"x": 1516, "y": 2328, "width": 225, "height": 133}, "scaleRatio": {"x": 1.0, "y": 1.0}, "isMulti": false, "isMip": false, "isAlpha8": false, "hull": []}, {"name": "Fx\\TartarusGhostHands\\TartarusGhostHands0082", "topLeft": {"x": 21, "y": 41}, "originalSize": {"x": 250, "y": 250}, "rect": {"x": 1543, "y": 1881, "width": 225, "height": 136}, "scaleRatio": {"x": 1.0, "y": 1.0}, "isMulti": false, "isMip": false, "isAlpha8": false, "hull": []}, {"name": "Fx\\TartarusGhostHands\\TartarusGhostHands0083", "topLeft": {"x": 21, "y": 42}, "originalSize": {"x": 250, "y": 250}, "rect": {"x": 1612, "y": 1182, "width": 225, "height": 135}, "scaleRatio": {"x": 1.0, "y": 1.0}, "isMulti": false, "isMip": false, "isAlpha8": false, "hull": []}, {"name": "Fx\\TartarusGhostHands\\TartarusGhostHands0084", "topLeft": {"x": 21, "y": 42}, "originalSize": {"x": 250, "y": 250}, "rect": {"x": 1630, "y": 951, "width": 225, "height": 136}, "scaleRatio": {"x": 1.0, "y": 1.0}, "isMulti": false, "isMip": false, "isAlpha8": false, "hull": []}, {"name": "Fx\\TartarusGhostHandsMulti\\TartarusGhostHandsMulti0001", "topLeft": {"x": 15, "y": 14}, "originalSize": {"x": 250, "y": 250}, "rect": {"x": 1569, "y": 1632, "width": 216, "height": 225}, "scaleRatio": {"x": 1.0, "y": 1.0}, "isMulti": false, "isMip": false, "isAlpha8": false, "hull": []}, {"name": "Fx\\TartarusGhostHandsMulti\\TartarusGhostHandsMulti0037", "topLeft": {"x": 24, "y": 21}, "originalSize": {"x": 250, "y": 250}, "rect": {"x": 1558, "y": 2017, "width": 225, "height": 225}, "scaleRatio": {"x": 1.0, "y": 1.0}, "isMulti": false, "isMip": false, "isAlpha8": false, "hull": []}, {"name": "Fx\\DashCrack\\DashCrack0039", "topLeft": {"x": 78, "y": 206}, "originalSize": {"x": 640, "y": 400}, "rect": {"x": 680, "y": 1694, "width": 224, "height": 83}, "scaleRatio": {"x": 1.0, "y": 1.0}, "isMulti": false, "isMip": false, "isAlpha8": false, "hull": []}, {"name": "Fx\\GunTrailB\\GunTrailB0003", "topLeft": {"x": 73, "y": 17}, "originalSize": {"x": 320, "y": 96}, "rect": {"x": 906, "y": 2806, "width": 224, "height": 73}, "scaleRatio": {"x": 1.0, "y": 1.0}, "isMulti": false, "isMip": false, "isAlpha8": false, "hull": []}, {"name": "Fx\\HadesFlameAura\\HadesFlameAura0002", "topLeft": {"x": 35, "y": 16}, "originalSize": {"x": 300, "y": 300}, "rect": {"x": 1759, "y": 728, "width": 224, "height": 188}, "scaleRatio": {"x": 1.0, "y": 1.0}, "isMulti": false, "isMip": false, "isAlpha8": false, "hull": []}, {"name": "Fx\\ProjectileFireRing\\ProjectileFireRing0138", "topLeft": {"x": 49, "y": 17}, "originalSize": {"x": 320, "y": 320}, "rect": {"x": 1770, "y": 1317, "width": 224, "height": 204}, "scaleRatio": {"x": 1.0, "y": 1.0}, "isMulti": false, "isMip": false, "isAlpha8": false, "hull": []}, {"name": "Fx\\ProjectileFireRing\\ProjectileFireRing0281", "topLeft": {"x": 3, "y": 57}, "originalSize": {"x": 320, "y": 320}, "rect": {"x": 1837, "y": 1087, "width": 142, "height": 224}, "scaleRatio": {"x": 1.0, "y": 1.0}, "isMulti": false, "isMip": false, "isAlpha8": false, "hull": []}, {"name": "Fx\\ProjectileFireRing\\ProjectileFireRing0323", "topLeft": {"x": 41, "y": 73}, "originalSize": {"x": 320, "y": 320}, "rect": {"x": 1583, "y": 2461, "width": 160, "height": 224}, "scaleRatio": {"x": 1.0, "y": 1.0}, "isMulti": false, "isMip": false, "isAlpha8": false, "hull": []}, {"name": "Fx\\ProjectileFireRing\\ProjectileFireRing0436", "topLeft": {"x": 127, "y": 84}, "originalSize": {"x": 320, "y": 320}, "rect": {"x": 1361, "y": 0, "width": 187, "height": 224}, "scaleRatio": {"x": 1.0, "y": 1.0}, "isMulti": false, "isMip": false, "isAlpha8": false, "hull": []}, {"name": "Fx\\ProjectileFireRing\\ProjectileFireRing0443", "topLeft": {"x": 118, "y": 80}, "originalSize": {"x": 320, "y": 320}, "rect": {"x": 1548, "y": 0, "width": 157, "height": 224}, "scaleRatio": {"x": 1.0, "y": 1.0}, "isMulti": false, "isMip": false, "isAlpha8": false, "hull": []}, {"name": "Fx\\ProjectileFireRing\\ProjectileFireRing0444", "topLeft": {"x": 118, "y": 79}, "originalSize": {"x": 320, "y": 320}, "rect": {"x": 1564, "y": 224, "width": 157, "height": 224}, "scaleRatio": {"x": 1.0, "y": 1.0}, "isMulti": false, "isMip": false, "isAlpha8": false, "hull": []}, {"name": "Fx\\ProjectileFireRing\\ProjectileFireRing0461", "topLeft": {"x": 187, "y": 58}, "originalSize": {"x": 320, "y": 320}, "rect": {"x": 1705, "y": 0, "width": 129, "height": 224}, "scaleRatio": {"x": 1.0, "y": 1.0}, "isMulti": false, "isMip": false, "isAlpha8": false, "hull": []}, {"name": "Fx\\ShadeSwordSwipeOverHead\\ShadeSwordSwipeOverHead0005", "topLeft": {"x": 190, "y": 9}, "originalSize": {"x": 400, "y": 400}, "rect": {"x": 1721, "y": 224, "width": 207, "height": 224}, "scaleRatio": {"x": 1.0, "y": 1.0}, "isMulti": false, "isMip": false, "isAlpha8": false, "hull": []}, {"name": "Fx\\ShadeTeleportCloud\\ShadeTeleportCloud0004", "topLeft": {"x": 160, "y": 55}, "originalSize": {"x": 480, "y": 240}, "rect": {"x": 1768, "y": 1857, "width": 224, "height": 131}, "scaleRatio": {"x": 1.0, "y": 1.0}, "isMulti": false, "isMip": false, "isAlpha8": false, "hull": []}, {"name": "Fx\\ShadeTeleportCloud\\ShadeTeleportCloud0008", "topLeft": {"x": 167, "y": 48}, "originalSize": {"x": 480, "y": 240}, "rect": {"x": 1855, "y": 916, "width": 224, "height": 142}, "scaleRatio": {"x": 1.0, "y": 1.0}, "isMulti": false, "isMip": false, "isAlpha8": false, "hull": []}, {"name": "Fx\\ShieldCharge\\ShieldCharge0029", "topLeft": {"x": 16, "y": 13}, "originalSize": {"x": 256, "y": 256}, "rect": {"x": 1834, "y": 0, "width": 216, "height": 224}, "scaleRatio": {"x": 1.0, "y": 1.0}, "isMulti": false, "isMip": false, "isAlpha8": false, "hull": []}, {"name": "Fx\\ShrineDoorLoop\\ShrineDoorLoop0039", "topLeft": {"x": 21, "y": 28}, "originalSize": {"x": 250, "y": 350}, "rect": {"x": 1979, "y": 1058, "width": 210, "height": 224}, "scaleRatio": {"x": 1.0, "y": 1.0}, "isMulti": false, "isMip": false, "isAlpha8": false, "hull": []}, {"name": "Fx\\ShrineDoorOpen\\ShrineDoorOpen0034", "topLeft": {"x": 22, "y": 25}, "originalSize": {"x": 250, "y": 350}, "rect": {"x": 1766, "y": 448, "width": 206, "height": 224}, "scaleRatio": {"x": 1.0, "y": 1.0}, "isMulti": false, "isMip": false, "isAlpha8": false, "hull": []}, {"name": "Fx\\SpikeTrapPressedOut\\SpikeTrapPressedOut0008", "topLeft": {"x": 65, "y": 110}, "originalSize": {"x": 340, "y": 400}, "rect": {"x": 1584, "y": 2685, "width": 224, "height": 143}, "scaleRatio": {"x": 1.0, "y": 1.0}, "isMulti": false, "isMip": false, "isAlpha8": false, "hull": []}, {"name": "Fx\\TartarusGhostHands\\TartarusGhostHands0022", "topLeft": {"x": 19, "y": 36}, "originalSize": {"x": 250, "y": 250}, "rect": {"x": 1741, "y": 2242, "width": 224, "height": 132}, "scaleRatio": {"x": 1.0, "y": 1.0}, "isMulti": false, "isMip": false, "isAlpha8": false, "hull": []}, {"name": "Fx\\TartarusGhostHands\\TartarusGhostHands0023", "topLeft": {"x": 19, "y": 35}, "originalSize": {"x": 250, "y": 250}, "rect": {"x": 1928, "y": 224, "width": 224, "height": 133}, "scaleRatio": {"x": 1.0, "y": 1.0}, "isMulti": false, "isMip": false, "isAlpha8": false, "hull": []}, {"name": "Fx\\TartarusGhostHands\\TartarusGhostHands0024", "topLeft": {"x": 19, "y": 34}, "originalSize": {"x": 250, "y": 250}, "rect": {"x": 2050, "y": 0, "width": 224, "height": 132}, "scaleRatio": {"x": 1.0, "y": 1.0}, "isMulti": false, "isMip": false, "isAlpha8": false, "hull": []}, {"name": "Fx\\TartarusGhostHandsMulti\\TartarusGhostHandsMulti0002", "topLeft": {"x": 16, "y": 14}, "originalSize": {"x": 250, "y": 250}, "rect": {"x": 1783, "y": 1988, "width": 214, "height": 224}, "scaleRatio": {"x": 1.0, "y": 1.0}, "isMulti": false, "isMip": false, "isAlpha8": false, "hull": []}, {"name": "Fx\\TartarusGhostHandsMulti\\TartarusGhostHandsMulti0035", "topLeft": {"x": 24, "y": 21}, "originalSize": {"x": 250, "y": 250}, "rect": {"x": 1743, "y": 2374, "width": 224, "height": 221}, "scaleRatio": {"x": 1.0, "y": 1.0}, "isMulti": false, "isMip": false, "isAlpha8": false, "hull": []}, {"name": "Fx\\TartarusGhostHandsMulti\\TartarusGhostHandsMulti0036", "topLeft": {"x": 24, "y": 21}, "originalSize": {"x": 250, "y": 250}, "rect": {"x": 1808, "y": 2595, "width": 224, "height": 222}, "scaleRatio": {"x": 1.0, "y": 1.0}, "isMulti": false, "isMip": false, "isAlpha8": false, "hull": []}, {"name": "Fx\\Temple_Urn_01_ShatterB\\Temple_Urn_01_ShatterB0004", "topLeft": {"x": 44, "y": 25}, "originalSize": {"x": 240, "y": 280}, "rect": {"x": 1785, "y": 1521, "width": 158, "height": 224}, "scaleRatio": {"x": 1.0, "y": 1.0}, "isMulti": false, "isMip": false, "isAlpha8": false, "hull": []}, {"name": "Fx\\ThanatosScytheLoop\\ThanatosScytheLoop0001", "topLeft": {"x": 40, "y": 46}, "originalSize": {"x": 240, "y": 320}, "rect": {"x": 1943, "y": 1521, "width": 125, "height": 224}, "scaleRatio": {"x": 1.0, "y": 1.0}, "isMulti": false, "isMip": false, "isAlpha8": false, "hull": []}, {"name": "Fx\\ThanatosScytheLoop\\ThanatosScytheLoop0003", "topLeft": {"x": 40, "y": 46}, "originalSize": {"x": 240, "y": 320}, "rect": {"x": 1994, "y": 1282, "width": 125, "height": 224}, "scaleRatio": {"x": 1.0, "y": 1.0}, "isMulti": false, "isMip": false, "isAlpha8": false, "hull": []}, {"name": "Fx\\ThanatosScytheLoop\\ThanatosScytheLoop0005", "topLeft": {"x": 41, "y": 46}, "originalSize": {"x": 240, "y": 320}, "rect": {"x": 1992, "y": 1745, "width": 125, "height": 224}, "scaleRatio": {"x": 1.0, "y": 1.0}, "isMulti": false, "isMip": false, "isAlpha8": false, "hull": []}, {"name": "Fx\\ThanatosScytheLoop\\ThanatosScytheLoop0006", "topLeft": {"x": 41, "y": 46}, "originalSize": {"x": 240, "y": 320}, "rect": {"x": 2068, "y": 1506, "width": 124, "height": 224}, "scaleRatio": {"x": 1.0, "y": 1.0}, "isMulti": false, "isMip": false, "isAlpha8": false, "hull": []}, {"name": "Fx\\ThanatosScytheLoop\\ThanatosScytheLoop0008", "topLeft": {"x": 40, "y": 46}, "originalSize": {"x": 240, "y": 320}, "rect": {"x": 2119, "y": 1282, "width": 127, "height": 224}, "scaleRatio": {"x": 1.0, "y": 1.0}, "isMulti": false, "isMip": false, "isAlpha8": false, "hull": []}, {"name": "Fx\\ThanatosScytheOut\\ThanatosScytheOut0001", "topLeft": {"x": 40, "y": 46}, "originalSize": {"x": 240, "y": 320}, "rect": {"x": 1972, "y": 357, "width": 125, "height": 224}, "scaleRatio": {"x": 1.0, "y": 1.0}, "isMulti": false, "isMip": false, "isAlpha8": false, "hull": []}, {"name": "Fx\\ThanatosScytheOut\\ThanatosScytheOut0003", "topLeft": {"x": 40, "y": 44}, "originalSize": {"x": 240, "y": 320}, "rect": {"x": 1983, "y": 581, "width": 125, "height": 224}, "scaleRatio": {"x": 1.0, "y": 1.0}, "isMulti": false, "isMip": false, "isAlpha8": false, "hull": []}, {"name": "Fx\\WarpGateLoop\\WarpGateLoop0012", "topLeft": {"x": 28, "y": 18}, "originalSize": {"x": 200, "y": 270}, "rect": {"x": 2097, "y": 357, "width": 146, "height": 224}, "scaleRatio": {"x": 1.0, "y": 1.0}, "isMulti": false, "isMip": false, "isAlpha8": false, "hull": []}, {"name": "Fx\\EurydiceShield\\EurydiceShield0021", "topLeft": {"x": 55, "y": 69}, "originalSize": {"x": 333, "y": 333}, "rect": {"x": 2152, "y": 132, "width": 223, "height": 187}, "scaleRatio": {"x": 1.0, "y": 1.0}, "isMulti": false, "isMip": false, "isAlpha8": false, "hull": []}, {"name": "Fx\\GunFireB\\GunFireB0007", "topLeft": {"x": 45, "y": 8}, "originalSize": {"x": 320, "y": 96}, "rect": {"x": 1358, "y": 2695, "width": 223, "height": 73}, "scaleRatio": {"x": 1.0, "y": 1.0}, "isMulti": false, "isMip": false, "isAlpha8": false, "hull": []}, {"name": "Fx\\HadesFlameAura\\HadesFlameAura0001", "topLeft": {"x": 37, "y": 10}, "originalSize": {"x": 300, "y": 300}, "rect": {"x": 2079, "y": 805, "width": 223, "height": 199}, "scaleRatio": {"x": 1.0, "y": 1.0}, "isMulti": false, "isMip": false, "isAlpha8": false, "hull": []}, {"name": "Fx\\HadesFlameAura\\HadesFlameAura0003", "topLeft": {"x": 37, "y": 26}, "originalSize": {"x": 300, "y": 300}, "rect": {"x": 2108, "y": 581, "width": 223, "height": 178}, "scaleRatio": {"x": 1.0, "y": 1.0}, "isMulti": false, "isMip": false, "isAlpha8": false, "hull": []}, {"name": "Fx\\ProjectileFireRing\\ProjectileFireRing0053", "topLeft": {"x": 153, "y": 31}, "originalSize": {"x": 320, "y": 320}, "rect": {"x": 2243, "y": 319, "width": 119, "height": 223}, "scaleRatio": {"x": 1.0, "y": 1.0}, "isMulti": false, "isMip": false, "isAlpha8": false, "hull": []}, {"name": "Fx\\ProjectileFireRing\\ProjectileFireRing0163", "topLeft": {"x": 23, "y": 20}, "originalSize": {"x": 320, "y": 320}, "rect": {"x": 2189, "y": 1004, "width": 223, "height": 189}, "scaleRatio": {"x": 1.0, "y": 1.0}, "isMulti": false, "isMip": false, "isAlpha8": false, "hull": []}, {"name": "Fx\\ProjectileFireRing\\ProjectileFireRing0166", "topLeft": {"x": 24, "y": 18}, "originalSize": {"x": 320, "y": 320}, "rect": {"x": 2302, "y": 759, "width": 223, "height": 197}, "scaleRatio": {"x": 1.0, "y": 1.0}, "isMulti": false, "isMip": false, "isAlpha8": false, "hull": []}, {"name": "Fx\\ProjectileFireRing\\ProjectileFireRing0370", "topLeft": {"x": 58, "y": 94}, "originalSize": {"x": 320, "y": 320}, "rect": {"x": 2525, "y": 0, "width": 223, "height": 223}, "scaleRatio": {"x": 1.0, "y": 1.0}, "isMulti": false, "isMip": false, "isAlpha8": false, "hull": []}, {"name": "Fx\\ProjectileFireRing\\ProjectileFireRing0403", "topLeft": {"x": 92, "y": 93}, "originalSize": {"x": 320, "y": 320}, "rect": {"x": 2525, "y": 223, "width": 223, "height": 223}, "scaleRatio": {"x": 1.0, "y": 1.0}, "isMulti": false, "isMip": false, "isAlpha8": false, "hull": []}, {"name": "Fx\\Shielded\\Shielded0028", "topLeft": {"x": 14, "y": 47}, "originalSize": {"x": 256, "y": 256}, "rect": {"x": 682, "y": 889, "width": 223, "height": 167}, "scaleRatio": {"x": 1.0, "y": 1.0}, "isMulti": false, "isMip": false, "isAlpha8": false, "hull": []}, {"name": "Fx\\Shielded\\Shielded0039", "topLeft": {"x": 13, "y": 48}, "originalSize": {"x": 256, "y": 256}, "rect": {"x": 2331, "y": 542, "width": 223, "height": 164}, "scaleRatio": {"x": 1.0, "y": 1.0}, "isMulti": false, "isMip": false, "isAlpha8": false, "hull": []}, {"name": "Fx\\Shielded\\Shielded0052", "topLeft": {"x": 22, "y": 47}, "originalSize": {"x": 256, "y": 256}, "rect": {"x": 2554, "y": 446, "width": 223, "height": 164}, "scaleRatio": {"x": 1.0, "y": 1.0}, "isMulti": false, "isMip": false, "isAlpha8": false, "hull": []}, {"name": "Fx\\ShrineDoorLoop\\ShrineDoorLoop0011", "topLeft": {"x": 22, "y": 27}, "originalSize": {"x": 250, "y": 350}, "rect": {"x": 2554, "y": 610, "width": 208, "height": 223}, "scaleRatio": {"x": 1.0, "y": 1.0}, "isMulti": false, "isMip": false, "isAlpha8": false, "hull": []}, {"name": "Fx\\TartarusGhostHands\\TartarusGhostHands0021", "topLeft": {"x": 20, "y": 36}, "originalSize": {"x": 250, "y": 250}, "rect": {"x": 2274, "y": 0, "width": 223, "height": 132}, "scaleRatio": {"x": 1.0, "y": 1.0}, "isMulti": false, "isMip": false, "isAlpha8": false, "hull": []}, {"name": "Fx\\TartarusGhostHands\\TartarusGhostHands0085", "topLeft": {"x": 21, "y": 42}, "originalSize": {"x": 250, "y": 250}, "rect": {"x": 1965, "y": 2212, "width": 223, "height": 136}, "scaleRatio": {"x": 1.0, "y": 1.0}, "isMulti": false, "isMip": false, "isAlpha8": false, "hull": []}, {"name": "Fx\\TartarusGhostHandsMulti\\TartarusGhostHandsMulti0003", "topLeft": {"x": 16, "y": 15}, "originalSize": {"x": 250, "y": 250}, "rect": {"x": 1997, "y": 1969, "width": 214, "height": 223}, "scaleRatio": {"x": 1.0, "y": 1.0}, "isMulti": false, "isMip": false, "isAlpha8": false, "hull": []}, {"name": "Fx\\TartarusGhostHandsMulti\\TartarusGhostHandsMulti0034", "topLeft": {"x": 24, "y": 21}, "originalSize": {"x": 250, "y": 250}, "rect": {"x": 2117, "y": 1730, "width": 223, "height": 219}, "scaleRatio": {"x": 1.0, "y": 1.0}, "isMulti": false, "isMip": false, "isAlpha8": false, "hull": []}, {"name": "Fx\\ThanatosScytheIn\\ThanatosScytheIn0005", "topLeft": {"x": 42, "y": 53}, "originalSize": {"x": 240, "y": 320}, "rect": {"x": 2192, "y": 1506, "width": 123, "height": 223}, "scaleRatio": {"x": 1.0, "y": 1.0}, "isMulti": false, "isMip": false, "isAlpha8": false, "hull": []}, {"name": "Fx\\ThanatosScytheIn\\ThanatosScytheIn0007", "topLeft": {"x": 41, "y": 47}, "originalSize": {"x": 240, "y": 320}, "rect": {"x": 2748, "y": 0, "width": 123, "height": 223}, "scaleRatio": {"x": 1.0, "y": 1.0}, "isMulti": false, "isMip": false, "isAlpha8": false, "hull": []}, {"name": "Fx\\ThanatosScytheIn\\ThanatosScytheIn0009", "topLeft": {"x": 41, "y": 47}, "originalSize": {"x": 240, "y": 320}, "rect": {"x": 2748, "y": 223, "width": 124, "height": 223}, "scaleRatio": {"x": 1.0, "y": 1.0}, "isMulti": false, "isMip": false, "isAlpha8": false, "hull": []}, {"name": "Fx\\ThanatosScytheLoop\\ThanatosScytheLoop0002", "topLeft": {"x": 40, "y": 47}, "originalSize": {"x": 240, "y": 320}, "rect": {"x": 1967, "y": 2348, "width": 126, "height": 223}, "scaleRatio": {"x": 1.0, "y": 1.0}, "isMulti": false, "isMip": false, "isAlpha8": false, "hull": []}, {"name": "Fx\\ThanatosScytheLoop\\ThanatosScytheLoop0004", "topLeft": {"x": 41, "y": 46}, "originalSize": {"x": 240, "y": 320}, "rect": {"x": 2375, "y": 132, "width": 124, "height": 223}, "scaleRatio": {"x": 1.0, "y": 1.0}, "isMulti": false, "isMip": false, "isAlpha8": false, "hull": []}, {"name": "Fx\\ThanatosScytheLoop\\ThanatosScytheLoop0026", "topLeft": {"x": 42, "y": 46}, "originalSize": {"x": 240, "y": 320}, "rect": {"x": 2032, "y": 2571, "width": 123, "height": 223}, "scaleRatio": {"x": 1.0, "y": 1.0}, "isMulti": false, "isMip": false, "isAlpha8": false, "hull": []}, {"name": "Fx\\ThanatosScytheLoop\\ThanatosScytheLoop0030", "topLeft": {"x": 41, "y": 47}, "originalSize": {"x": 240, "y": 320}, "rect": {"x": 2093, "y": 2348, "width": 124, "height": 223}, "scaleRatio": {"x": 1.0, "y": 1.0}, "isMulti": false, "isMip": false, "isAlpha8": false, "hull": []}, {"name": "Fx\\ThanatosScytheOut\\ThanatosScytheOut0002", "topLeft": {"x": 40, "y": 46}, "originalSize": {"x": 240, "y": 320}, "rect": {"x": 2155, "y": 2571, "width": 126, "height": 223}, "scaleRatio": {"x": 1.0, "y": 1.0}, "isMulti": false, "isMip": false, "isAlpha8": false, "hull": []}, {"name": "Fx\\DashPuff\\DashPuff0010", "topLeft": {"x": 131, "y": 19}, "originalSize": {"x": 480, "y": 135}, "rect": {"x": 227, "y": 2481, "width": 222, "height": 107}, "scaleRatio": {"x": 1.0, "y": 1.0}, "isMulti": false, "isMip": false, "isAlpha8": false, "hull": []}, {"name": "Fx\\DashPuff\\DashPuff0030", "topLeft": {"x": 152, "y": 37}, "originalSize": {"x": 480, "y": 135}, "rect": {"x": 2189, "y": 1193, "width": 222, "height": 88}, "scaleRatio": {"x": 1.0, "y": 1.0}, "isMulti": false, "isMip": false, "isAlpha8": false, "hull": []}, {"name": "Fx\\Elysium_Urn_01_ShatterB\\Elysium_Urn_01_ShatterB0010", "topLeft": {"x": 0, "y": 57}, "originalSize": {"x": 240, "y": 280}, "rect": {"x": 2246, "y": 1281, "width": 222, "height": 185}, "scaleRatio": {"x": 1.0, "y": 1.0}, "isMulti": false, "isMip": false, "isAlpha8": false, "hull": []}, {"name": "Fx\\HadesFlameAura\\HadesFlameAura0005", "topLeft": {"x": 39, "y": 28}, "originalSize": {"x": 300, "y": 300}, "rect": {"x": 2315, "y": 1466, "width": 222, "height": 171}, "scaleRatio": {"x": 1.0, "y": 1.0}, "isMulti": false, "isMip": false, "isAlpha8": false, "hull": []}, {"name": "Fx\\MainMenuBloodstone\\MainMenuBloodstone0043", "topLeft": {"x": 31, "y": 164}, "originalSize": {"x": 300, "y": 400}, "rect": {"x": 2537, "y": 833, "width": 222, "height": 165}, "scaleRatio": {"x": 1.0, "y": 1.0}, "isMulti": false, "isMip": false, "isAlpha8": false, "hull": []}, {"name": "Fx\\ProjectileFireRing\\ProjectileFireRing0011", "topLeft": {"x": 191, "y": 45}, "originalSize": {"x": 320, "y": 320}, "rect": {"x": 2762, "y": 610, "width": 117, "height": 222}, "scaleRatio": {"x": 1.0, "y": 1.0}, "isMulti": false, "isMip": false, "isAlpha8": false, "hull": []}, {"name": "Fx\\ProjectileFireRing\\ProjectileFireRing0226", "topLeft": {"x": 20, "y": 29}, "originalSize": {"x": 320, "y": 320}, "rect": {"x": 2412, "y": 998, "width": 132, "height": 222}, "scaleRatio": {"x": 1.0, "y": 1.0}, "isMulti": false, "isMip": false, "isAlpha8": false, "hull": []}, {"name": "Fx\\ProjectileFireRing\\ProjectileFireRing0414", "topLeft": {"x": 78, "y": 92}, "originalSize": {"x": 320, "y": 320}, "rect": {"x": 2468, "y": 1220, "width": 222, "height": 203}, "scaleRatio": {"x": 1.0, "y": 1.0}, "isMulti": false, "isMip": false, "isAlpha8": false, "hull": []}, {"name": "Fx\\ProjectileHelix\\ProjectileHelix0013", "topLeft": {"x": 71, "y": 0}, "originalSize": {"x": 320, "y": 64}, "rect": {"x": 444, "y": 2194, "width": 222, "height": 58}, "scaleRatio": {"x": 1.0, "y": 1.0}, "isMulti": false, "isMip": false, "isAlpha8": false, "hull": []}, {"name": "Fx\\RatDeathB\\RatDeathB0015", "topLeft": {"x": 18, "y": 34}, "originalSize": {"x": 240, "y": 240}, "rect": {"x": 2188, "y": 2192, "width": 222, "height": 139}, "scaleRatio": {"x": 1.0, "y": 1.0}, "isMulti": false, "isMip": false, "isAlpha8": false, "hull": []}, {"name": "Fx\\Shielded\\Shielded0002", "topLeft": {"x": 19, "y": 45}, "originalSize": {"x": 256, "y": 256}, "rect": {"x": 2544, "y": 998, "width": 222, "height": 166}, "scaleRatio": {"x": 1.0, "y": 1.0}, "isMulti": false, "isMip": false, "isAlpha8": false, "hull": []}, {"name": "Fx\\ShrineDoorLoop\\ShrineDoorLoop0034", "topLeft": {"x": 22, "y": 27}, "originalSize": {"x": 250, "y": 350}, "rect": {"x": 2217, "y": 2331, "width": 206, "height": 222}, "scaleRatio": {"x": 1.0, "y": 1.0}, "isMulti": false, "isMip": false, "isAlpha8": false, "hull": []}, {"name": "Fx\\ShrineDoorOpen\\ShrineDoorOpen0033", "topLeft": {"x": 22, "y": 27}, "originalSize": {"x": 250, "y": 350}, "rect": {"x": 2211, "y": 1949, "width": 206, "height": 222}, "scaleRatio": {"x": 1.0, "y": 1.0}, "isMulti": false, "isMip": false, "isAlpha8": false, "hull": []}, {"name": "Fx\\SpikeTrapPressedOut\\SpikeTrapPressedOut0009", "topLeft": {"x": 66, "y": 121}, "originalSize": {"x": 340, "y": 400}, "rect": {"x": 2410, "y": 2171, "width": 222, "height": 132}, "scaleRatio": {"x": 1.0, "y": 1.0}, "isMulti": false, "isMip": false, "isAlpha8": false, "hull": []}, {"name": "Fx\\TartarusGhostHands\\TartarusGhostHands0017", "topLeft": {"x": 20, "y": 39}, "originalSize": {"x": 250, "y": 250}, "rect": {"x": 2632, "y": 1423, "width": 222, "height": 134}, "scaleRatio": {"x": 1.0, "y": 1.0}, "isMulti": false, "isMip": false, "isAlpha8": false, "hull": []}, {"name": "Fx\\TartarusGhostHands\\TartarusGhostHands0018", "topLeft": {"x": 20, "y": 39}, "originalSize": {"x": 250, "y": 250}, "rect": {"x": 2632, "y": 1557, "width": 222, "height": 133}, "scaleRatio": {"x": 1.0, "y": 1.0}, "isMulti": false, "isMip": false, "isAlpha8": false, "hull": []}, {"name": "Fx\\TartarusGhostHands\\TartarusGhostHands0019", "topLeft": {"x": 20, "y": 38}, "originalSize": {"x": 250, "y": 250}, "rect": {"x": 2632, "y": 1690, "width": 222, "height": 132}, "scaleRatio": {"x": 1.0, "y": 1.0}, "isMulti": false, "isMip": false, "isAlpha8": false, "hull": []}, {"name": "Fx\\TartarusGhostHands\\TartarusGhostHands0020", "topLeft": {"x": 20, "y": 37}, "originalSize": {"x": 250, "y": 250}, "rect": {"x": 2632, "y": 1822, "width": 222, "height": 132}, "scaleRatio": {"x": 1.0, "y": 1.0}, "isMulti": false, "isMip": false, "isAlpha8": false, "hull": []}, {"name": "Fx\\TartarusGhostHands\\TartarusGhostHands0087", "topLeft": {"x": 21, "y": 42}, "originalSize": {"x": 250, "y": 250}, "rect": {"x": 2632, "y": 1954, "width": 222, "height": 136}, "scaleRatio": {"x": 1.0, "y": 1.0}, "isMulti": false, "isMip": false, "isAlpha8": false, "hull": []}, {"name": "Fx\\TartarusGhostHands\\TartarusGhostHands0088", "topLeft": {"x": 21, "y": 42}, "originalSize": {"x": 250, "y": 250}, "rect": {"x": 2632, "y": 2090, "width": 222, "height": 135}, "scaleRatio": {"x": 1.0, "y": 1.0}, "isMulti": false, "isMip": false, "isAlpha8": false, "hull": []}, {"name": "Fx\\TartarusGhostHandsMulti\\TartarusGhostHandsMulti0004", "topLeft": {"x": 16, "y": 15}, "originalSize": {"x": 250, "y": 250}, "rect": {"x": 2417, "y": 1822, "width": 213, "height": 222}, "scaleRatio": {"x": 1.0, "y": 1.0}, "isMulti": false, "isMip": false, "isAlpha8": false, "hull": []}, {"name": "Fx\\TartarusGhostHandsMulti\\TartarusGhostHandsMulti0033", "topLeft": {"x": 24, "y": 21}, "originalSize": {"x": 250, "y": 250}, "rect": {"x": 2632, "y": 2225, "width": 222, "height": 218}, "scaleRatio": {"x": 1.0, "y": 1.0}, "isMulti": false, "isMip": false, "isAlpha8": false, "hull": []}, {"name": "Fx\\ThanatosScytheLoop\\ThanatosScytheLoop0007", "topLeft": {"x": 40, "y": 47}, "originalSize": {"x": 240, "y": 320}, "rect": {"x": 2690, "y": 1164, "width": 126, "height": 222}, "scaleRatio": {"x": 1.0, "y": 1.0}, "isMulti": false, "isMip": false, "isAlpha8": false, "hull": []}, {"name": "Fx\\ThanatosScytheLoop\\ThanatosScytheLoop0028", "topLeft": {"x": 41, "y": 46}, "originalSize": {"x": 240, "y": 320}, "rect": {"x": 2423, "y": 2303, "width": 123, "height": 222}, "scaleRatio": {"x": 1.0, "y": 1.0}, "isMulti": false, "isMip": false, "isAlpha8": false, "hull": []}, {"name": "Fx\\WarpGateLoop\\WarpGateLoop0049", "topLeft": {"x": 27, "y": 24}, "originalSize": {"x": 200, "y": 270}, "rect": {"x": 2281, "y": 2553, "width": 148, "height": 222}, "scaleRatio": {"x": 1.0, "y": 1.0}, "isMulti": false, "isMip": false, "isAlpha8": false, "hull": []}, {"name": "Fx\\GunTrailB\\GunTrailB0007", "topLeft": {"x": 63, "y": 13}, "originalSize": {"x": 320, "y": 96}, "rect": {"x": 1808, "y": 2817, "width": 221, "height": 63}, "scaleRatio": {"x": 1.0, "y": 1.0}, "isMulti": false, "isMip": false, "isAlpha8": false, "hull": []}, {"name": "Fx\\HadesFlameAura\\HadesFlameAura0004", "topLeft": {"x": 40, "y": 27}, "originalSize": {"x": 300, "y": 300}, "rect": {"x": 2340, "y": 1637, "width": 221, "height": 166}, "scaleRatio": {"x": 1.0, "y": 1.0}, "isMulti": false, "isMip": false, "isAlpha8": false, "hull": []}, {"name": "Fx\\HadesFlameAura\\HadesFlameAura0006", "topLeft": {"x": 40, "y": 28}, "originalSize": {"x": 300, "y": 300}, "rect": {"x": 2546, "y": 2443, "width": 221, "height": 161}, "scaleRatio": {"x": 1.0, "y": 1.0}, "isMulti": false, "isMip": false, "isAlpha8": false, "hull": []}, {"name": "Fx\\RoomRewardTransition\\RoomRewardTransition0009", "topLeft": {"x": 53, "y": 31}, "originalSize": {"x": 320, "y": 320}, "rect": {"x": 2429, "y": 2604, "width": 221, "height": 204}, "scaleRatio": {"x": 1.0, "y": 1.0}, "isMulti": false, "isMip": false, "isAlpha8": false, "hull": []}, {"name": "Fx\\ShadeTrail\\ShadeTrail0031", "topLeft": {"x": 84, "y": 141}, "originalSize": {"x": 333, "y": 333}, "rect": {"x": 2650, "y": 2604, "width": 221, "height": 163}, "scaleRatio": {"x": 1.0, "y": 1.0}, "isMulti": false, "isMip": false, "isAlpha8": false, "hull": []}, {"name": "Fx\\HydraTouchdownCracks\\HydraTouchdownCracks0005", "topLeft": {"x": 150, "y": 74}, "originalSize": {"x": 512, "y": 256}, "rect": {"x": 2650, "y": 2767, "width": 220, "height": 111}, "scaleRatio": {"x": 1.0, "y": 1.0}, "isMulti": false, "isMip": false, "isAlpha8": false, "hull": []}, {"name": "Fx\\ShieldEmpowerBack\\ShieldEmpowerBack0013", "topLeft": {"x": 41, "y": 61}, "originalSize": {"x": 320, "y": 240}, "rect": {"x": 2032, "y": 2794, "width": 220, "height": 81}, "scaleRatio": {"x": 1.0, "y": 1.0}, "isMulti": false, "isMip": false, "isAlpha8": false, "hull": []}, {"name": "Fx\\ProjectileFireRing\\ProjectileFireRing0054", "topLeft": {"x": 152, "y": 34}, "originalSize": {"x": 320, "y": 320}, "rect": {"x": 2766, "y": 832, "width": 114, "height": 218}, "scaleRatio": {"x": 1.0, "y": 1.0}, "isMulti": false, "isMip": false, "isAlpha8": false, "hull": []}, {"name": "Fx\\SpikeTrapPressedOut\\SpikeTrapPressedOut0011", "topLeft": {"x": 69, "y": 140}, "originalSize": {"x": 340, "y": 400}, "rect": {"x": 887, "y": 547, "width": 217, "height": 113}, "scaleRatio": {"x": 1.0, "y": 1.0}, "isMulti": false, "isMip": false, "isAlpha8": false, "hull": []}, {"name": "Fx\\GunTrailB\\GunTrailB0006", "topLeft": {"x": 67, "y": 15}, "originalSize": {"x": 320, "y": 96}, "rect": {"x": 455, "y": 1056, "width": 215, "height": 61}, "scaleRatio": {"x": 1.0, "y": 1.0}, "isMulti": false, "isMip": false, "isAlpha8": false, "hull": []}, {"name": "Fx\\ShadeTeleportCloud\\ShadeTeleportCloud0003", "topLeft": {"x": 159, "y": 57}, "originalSize": {"x": 480, "y": 240}, "rect": {"x": 2417, "y": 2044, "width": 215, "height": 123}, "scaleRatio": {"x": 1.0, "y": 1.0}, "isMulti": false, "isMip": false, "isAlpha8": false, "hull": []}, {"name": "Fx\\GunTrailB\\GunTrailB0015", "topLeft": {"x": 49, "y": 23}, "originalSize": {"x": 320, "y": 96}, "rect": {"x": 1766, "y": 672, "width": 211, "height": 55}, "scaleRatio": {"x": 1.0, "y": 1.0}, "isMulti": false, "isMip": false, "isAlpha8": false, "hull": []}, {"name": "Fx\\ProjectileFireRing\\ProjectileFireRing0475", "topLeft": {"x": 163, "y": 68}, "originalSize": {"x": 320, "y": 320}, "rect": {"x": 2537, "y": 1423, "width": 91, "height": 209}, "scaleRatio": {"x": 1.0, "y": 1.0}, "isMulti": false, "isMip": false, "isAlpha8": false, "hull": []}, {"name": "Fx\\GunFireB\\GunFireB0002", "topLeft": {"x": 88, "y": 16}, "originalSize": {"x": 320, "y": 96}, "rect": {"x": 1584, "y": 2828, "width": 207, "height": 52}, "scaleRatio": {"x": 1.0, "y": 1.0}, "isMulti": false, "isMip": false, "isAlpha8": false, "hull": []}, {"name": "Fx\\ShadeTeleportCloud\\ShadeTeleportCloud0002", "topLeft": {"x": 158, "y": 62}, "originalSize": {"x": 480, "y": 240}, "rect": {"x": 1785, "y": 1745, "width": 203, "height": 110}, "scaleRatio": {"x": 1.0, "y": 1.0}, "isMulti": false, "isMip": false, "isAlpha8": false, "hull": []}, {"name": "Fx\\MainMenuBloodstone\\MainMenuBloodstone0038", "topLeft": {"x": 42, "y": 210}, "originalSize": {"x": 300, "y": 400}, "rect": {"x": 1361, "y": 224, "width": 201, "height": 113}, "scaleRatio": {"x": 1.0, "y": 1.0}, "isMulti": false, "isMip": false, "isAlpha8": false, "hull": []}, {"name": "Fx\\ProjectileHelix\\ProjectileHelix0019", "topLeft": {"x": 62, "y": 4}, "originalSize": {"x": 320, "y": 64}, "rect": {"x": 2331, "y": 706, "width": 197, "height": 53}, "scaleRatio": {"x": 1.0, "y": 1.0}, "isMulti": false, "isMip": false, "isAlpha8": false, "hull": []}, {"name": "Fx\\ShadeBowTrailB\\ShadeBowTrailB0002", "topLeft": {"x": 71, "y": 6}, "originalSize": {"x": 320, "y": 96}, "rect": {"x": 682, "y": 342, "width": 196, "height": 85}, "scaleRatio": {"x": 1.0, "y": 1.0}, "isMulti": false, "isMip": false, "isAlpha8": false, "hull": []}, {"name": "Fx\\CandleWisp\\CandleWisp0044", "topLeft": {"x": 22, "y": 41}, "originalSize": {"x": 80, "y": 240}, "rect": {"x": 2816, "y": 1050, "width": 55, "height": 195}, "scaleRatio": {"x": 1.0, "y": 1.0}, "isMulti": false, "isMip": false, "isAlpha8": false, "hull": []}, {"name": "Fx\\ProjectileHelix\\ProjectileHelix0018", "topLeft": {"x": 71, "y": 3}, "originalSize": {"x": 320, "y": 64}, "rect": {"x": 1564, "y": 448, "width": 194, "height": 53}, "scaleRatio": {"x": 1.0, "y": 1.0}, "isMulti": false, "isMip": false, "isAlpha8": false, "hull": []}, {"name": "Fx\\GunTrailB\\GunTrailB0026", "topLeft": {"x": 54, "y": 24}, "originalSize": {"x": 320, "y": 96}, "rect": {"x": 2108, "y": 759, "width": 193, "height": 46}, "scaleRatio": {"x": 1.0, "y": 1.0}, "isMulti": false, "isMip": false, "isAlpha8": false, "hull": []}, {"name": "Fx\\ShadeBowTrailA\\ShadeBowTrailA0004", "topLeft": {"x": 70, "y": 5}, "originalSize": {"x": 320, "y": 96}, "rect": {"x": 1630, "y": 1087, "width": 193, "height": 89}, "scaleRatio": {"x": 1.0, "y": 1.0}, "isMulti": false, "isMip": false, "isAlpha8": false, "hull": []}, {"name": "Fx\\ShadeSpike\\ShadeSpike0017", "topLeft": {"x": 131, "y": 45}, "originalSize": {"x": 320, "y": 180}, "rect": {"x": 2362, "y": 446, "width": 189, "height": 93}, "scaleRatio": {"x": 1.0, "y": 1.0}, "isMulti": false, "isMip": false, "isAlpha8": false, "hull": []}, {"name": "Fx\\ProjectileFireRing\\ProjectileFireRing0058", "topLeft": {"x": 180, "y": 54}, "originalSize": {"x": 320, "y": 320}, "rect": {"x": 2561, "y": 1632, "width": 67, "height": 187}, "scaleRatio": {"x": 1.0, "y": 1.0}, "isMulti": false, "isMip": false, "isAlpha8": false, "hull": []}, {"name": "Fx\\GunTrailA\\GunTrailA0028", "topLeft": {"x": 45, "y": 20}, "originalSize": {"x": 320, "y": 96}, "rect": {"x": 2252, "y": 2808, "width": 185, "height": 48}, "scaleRatio": {"x": 1.0, "y": 1.0}, "isMulti": false, "isMip": false, "isAlpha8": false, "hull": []}, {"name": "Fx\\ProjectileHelix\\ProjectileHelix0029", "topLeft": {"x": 40, "y": 8}, "originalSize": {"x": 320, "y": 64}, "rect": {"x": 2437, "y": 2808, "width": 182, "height": 49}, "scaleRatio": {"x": 1.0, "y": 1.0}, "isMulti": false, "isMip": false, "isAlpha8": false, "hull": []}, {"name": "Fx\\ShadeTeleportCloud\\ShadeTeleportCloud0028", "topLeft": {"x": 208, "y": 63}, "originalSize": {"x": 480, "y": 240}, "rect": {"x": 1558, "y": 2242, "width": 182, "height": 83}, "scaleRatio": {"x": 1.0, "y": 1.0}, "isMulti": false, "isMip": false, "isAlpha8": false, "hull": []}, {"name": "Fx\\EnemyWringerChainGrab\\EnemyWringerChainGrab0033", "topLeft": {"x": 14, "y": 109}, "originalSize": {"x": 240, "y": 240}, "rect": {"x": 905, "y": 2115, "width": 176, "height": 73}, "scaleRatio": {"x": 1.0, "y": 1.0}, "isMulti": false, "isMip": false, "isAlpha8": false, "hull": []}, {"name": "Fx\\ShrinePointObject\\ShrinePointObject0011", "topLeft": {"x": 77, "y": 53}, "originalSize": {"x": 256, "y": 256}, "rect": {"x": 2777, "y": 446, "width": 99, "height": 164}, "scaleRatio": {"x": 1.0, "y": 1.0}, "isMulti": false, "isMip": false, "isAlpha8": false, "hull": []}, {"name": "Fx\\ShrinePointObject\\ShrinePointObject0010", "topLeft": {"x": 78, "y": 52}, "originalSize": {"x": 256, "y": 256}, "rect": {"x": 2767, "y": 2443, "width": 97, "height": 161}, "scaleRatio": {"x": 1.0, "y": 1.0}, "isMulti": false, "isMip": false, "isAlpha8": false, "hull": []}, {"name": "Fx\\PoisonPoolOut\\PoisonPoolOut0008", "topLeft": {"x": 24, "y": 5}, "originalSize": {"x": 240, "y": 120}, "rect": {"x": 2362, "y": 355, "width": 160, "height": 91}, "scaleRatio": {"x": 1.0, "y": 1.0}, "isMulti": false, "isMip": false, "isAlpha8": false, "hull": []}, {"name": "Fx\\DashCrack\\DashCrack0047", "topLeft": {"x": 256, "y": 206}, "originalSize": {"x": 640, "y": 400}, "rect": {"x": 2816, "y": 1245, "width": 64, "height": 155}, "scaleRatio": {"x": 1.0, "y": 1.0}, "isMulti": false, "isMip": false, "isAlpha8": false, "hull": []}, {"name": "Fx\\StyxThiefDeath\\StyxThiefDeath0022", "topLeft": {"x": 59, "y": 98}, "originalSize": {"x": 300, "y": 320}, "rect": {"x": 1612, "y": 1317, "width": 155, "height": 90}, "scaleRatio": {"x": 1.0, "y": 1.0}, "isMulti": false, "isMip": false, "isAlpha8": false, "hull": []}, {"name": "Fx\\ElysiumGrassTuftA\\ElysiumGrassTuftA0009", "topLeft": {"x": 6, "y": 15}, "originalSize": {"x": 160, "y": 120}, "rect": {"x": 452, "y": 1283, "width": 153, "height": 60}, "scaleRatio": {"x": 1.0, "y": 1.0}, "isMulti": false, "isMip": false, "isAlpha8": false, "hull": []}, {"name": "Fx\\GunFireADark\\GunFireADark0013", "topLeft": {"x": 43, "y": 24}, "originalSize": {"x": 320, "y": 96}, "rect": {"x": 2544, "y": 1164, "width": 136, "height": 56}, "scaleRatio": {"x": 1.0, "y": 1.0}, "isMulti": false, "isMip": false, "isAlpha8": false, "hull": []}, {"name": "Fx\\ElysiumGrassTuftC\\ElysiumGrassTuftC0018", "topLeft": {"x": 7, "y": 6}, "originalSize": {"x": 140, "y": 40}, "rect": {"x": 2340, "y": 1803, "width": 124, "height": 19}, "scaleRatio": {"x": 1.0, "y": 1.0}, "isMulti": false, "isMip": false, "isAlpha8": false, "hull": []}, {"name": "Fx\\GunMuzzleFlash\\GunMuzzleFlash3D\\GunMuzzleFlash3D0001", "topLeft": {"x": 170, "y": 113}, "originalSize": {"x": 360, "y": 360}, "rect": {"x": 2546, "y": 2303, "width": 84, "height": 123}, "scaleRatio": {"x": 1.0, "y": 1.0}, "isMulti": false, "isMip": false, "isAlpha8": false, "hull": []}, {"name": "Fx\\ShadeNakedFlame\\ShadeNakedFlame0056", "topLeft": {"x": 77, "y": 36}, "originalSize": {"x": 220, "y": 240}, "rect": {"x": 1290, "y": 2469, "width": 68, "height": 121}, "scaleRatio": {"x": 1.0, "y": 1.0}, "isMulti": false, "isMip": false, "isAlpha8": false, "hull": []}, {"name": "Fx\\PointedProjectile\\PointedProjectile0018", "topLeft": {"x": 99, "y": 90}, "originalSize": {"x": 256, "y": 256}, "rect": {"x": 2429, "y": 2525, "width": 115, "height": 76}, "scaleRatio": {"x": 1.0, "y": 1.0}, "isMulti": false, "isMip": false, "isAlpha8": false, "hull": []}, {"name": "Fx\\ShadeNakedFlame\\ShadeNakedFlame0048", "topLeft": {"x": 78, "y": 39}, "originalSize": {"x": 220, "y": 240}, "rect": {"x": 2340, "y": 1822, "width": 67, "height": 115}, "scaleRatio": {"x": 1.0, "y": 1.0}, "isMulti": false, "isMip": false, "isAlpha8": false, "hull": []}, {"name": "Fx\\BlastUrnRegen\\BlastUrnRegen0030", "topLeft": {"x": 34, "y": 73}, "originalSize": {"x": 157, "y": 191}, "rect": {"x": 1983, "y": 805, "width": 88, "height": 111}, "scaleRatio": {"x": 1.0, "y": 1.0}, "isMulti": false, "isMip": false, "isAlpha8": false, "hull": []}, {"name": "Fx\\GunFireBDark\\GunFireBDark0020", "topLeft": {"x": 41, "y": 25}, "originalSize": {"x": 320, "y": 96}, "rect": {"x": 2079, "y": 1004, "width": 109, "height": 53}, "scaleRatio": {"x": 1.0, "y": 1.0}, "isMulti": false, "isMip": false, "isAlpha8": false, "hull": []}, {"name": "Fx\\GunHomingBullet\\GunHomingBullet0017", "topLeft": {"x": 125, "y": 72}, "originalSize": {"x": 256, "y": 256}, "rect": {"x": 2050, "y": 132, "width": 102, "height": 85}, "scaleRatio": {"x": 1.0, "y": 1.0}, "isMulti": false, "isMip": false, "isAlpha8": false, "hull": []}, {"name": "Fx\\GunTrailA\\GunTrailA0033", "topLeft": {"x": 57, "y": 20}, "originalSize": {"x": 320, "y": 96}, "rect": {"x": 2302, "y": 956, "width": 102, "height": 47}, "scaleRatio": {"x": 1.0, "y": 1.0}, "isMulti": false, "isMip": false, "isAlpha8": false, "hull": []}, {"name": "Fx\\ShadeNakedFlameSingleC\\ShadeNakedFlameSingleC0007", "topLeft": {"x": 84, "y": 57}, "originalSize": {"x": 220, "y": 240}, "rect": {"x": 1928, "y": 357, "width": 44, "height": 83}, "scaleRatio": {"x": 1.0, "y": 1.0}, "isMulti": false, "isMip": false, "isAlpha8": false, "hull": []}, {"name": "Fx\\ShadeNakedFlameSingleB\\ShadeNakedFlameSingleB0014", "topLeft": {"x": 83, "y": 62}, "originalSize": {"x": 220, "y": 240}, "rect": {"x": 2766, "y": 1050, "width": 47, "height": 79}, "scaleRatio": {"x": 1.0, "y": 1.0}, "isMulti": false, "isMip": false, "isAlpha8": false, "hull": []}, {"name": "Fx\\GunFireBDark\\GunFireBDark0021", "topLeft": {"x": 39, "y": 25}, "originalSize": {"x": 320, "y": 96}, "rect": {"x": 605, "y": 1488, "width": 75, "height": 54}, "scaleRatio": {"x": 1.0, "y": 1.0}, "isMulti": false, "isMip": false, "isAlpha8": false, "hull": []}, {"name": "Fx\\GunFireBDark\\GunFireBDark0025", "topLeft": {"x": 38, "y": 28}, "originalSize": {"x": 320, "y": 96}, "rect": {"x": 1339, "y": 503, "width": 75, "height": 44}, "scaleRatio": {"x": 1.0, "y": 1.0}, "isMulti": false, "isMip": false, "isAlpha8": false, "hull": []}, {"name": "Fx\\ElysiumButterflyCycleC\\ElysiumButterflyCycleC0067", "topLeft": {"x": 8, "y": 51}, "originalSize": {"x": 270, "y": 200}, "rect": {"x": 1414, "y": 503, "width": 73, "height": 44}, "scaleRatio": {"x": 1.0, "y": 1.0}, "isMulti": false, "isMip": false, "isAlpha8": false, "hull": []}, {"name": "Fx\\SnowFootstepHades\\SnowFootstepHades0141", "topLeft": {"x": 16, "y": 27}, "originalSize": {"x": 100, "y": 100}, "rect": {"x": 2468, "y": 1423, "width": 69, "height": 43}, "scaleRatio": {"x": 1.0, "y": 1.0}, "isMulti": false, "isMip": false, "isAlpha8": false, "hull": []}, {"name": "Fx\\ElysiumButterflyCycleC\\ElysiumButterflyCycleC0016", "topLeft": {"x": 165, "y": 72}, "originalSize": {"x": 270, "y": 200}, "rect": {"x": 680, "y": 2605, "width": 67, "height": 43}, "scaleRatio": {"x": 1.0, "y": 1.0}, "isMulti": false, "isMip": false, "isAlpha8": false, "hull": []}, {"name": "Fx\\SnowFootstepHades\\SnowFootstepHades0109", "topLeft": {"x": 16, "y": 27}, "originalSize": {"x": 100, "y": 100}, "rect": {"x": 1487, "y": 503, "width": 67, "height": 44}, "scaleRatio": {"x": 1.0, "y": 1.0}, "isMulti": false, "isMip": false, "isAlpha8": false, "hull": []}, {"name": "Fx\\RatDeathB\\RatDeathB0002", "topLeft": {"x": 85, "y": 75}, "originalSize": {"x": 240, "y": 240}, "rect": {"x": 1743, "y": 2595, "width": 65, "height": 44}, "scaleRatio": {"x": 1.0, "y": 1.0}, "isMulti": false, "isMip": false, "isAlpha8": false, "hull": []}, {"name": "Fx\\SnowFootstepHades\\SnowFootstepHades0229", "topLeft": {"x": 18, "y": 27}, "originalSize": {"x": 100, "y": 100}, "rect": {"x": 1743, "y": 2639, "width": 64, "height": 46}, "scaleRatio": {"x": 1.0, "y": 1.0}, "isMulti": false, "isMip": false, "isAlpha8": false, "hull": []}, {"name": "Fx\\ElysiumButterflyCycleB\\ElysiumButterflyCycleB0031", "topLeft": {"x": 16, "y": 38}, "originalSize": {"x": 90, "y": 180}, "rect": {"x": 747, "y": 2605, "width": 61, "height": 43}, "scaleRatio": {"x": 1.0, "y": 1.0}, "isMulti": false, "isMip": false, "isAlpha8": false, "hull": []}, {"name": "Fx\\ElysiumButterflyCycleD\\ElysiumButterflyCycleD0065", "topLeft": {"x": 11, "y": 27}, "originalSize": {"x": 200, "y": 200}, "rect": {"x": 808, "y": 2605, "width": 60, "height": 43}, "scaleRatio": {"x": 1.0, "y": 1.0}, "isMulti": false, "isMip": false, "isAlpha8": false, "hull": []}, {"name": "Fx\\ElysiumButterflyCycleD\\ElysiumButterflyCycleD0025", "topLeft": {"x": 28, "y": 58}, "originalSize": {"x": 200, "y": 200}, "rect": {"x": 2243, "y": 542, "width": 59, "height": 39}, "scaleRatio": {"x": 1.0, "y": 1.0}, "isMulti": false, "isMip": false, "isAlpha8": false, "hull": []}, {"name": "Fx\\ElysiumButterflyCycleB\\ElysiumButterflyCycleB0011", "topLeft": {"x": 17, "y": 6}, "originalSize": {"x": 90, "y": 180}, "rect": {"x": 2411, "y": 1220, "width": 57, "height": 48}, "scaleRatio": {"x": 1.0, "y": 1.0}, "isMulti": false, "isMip": false, "isAlpha8": false, "hull": []}, {"name": "Fx\\SnowFootstepZag\\SnowFootstepZag0015", "topLeft": {"x": 11, "y": 22}, "originalSize": {"x": 80, "y": 80}, "rect": {"x": 2404, "y": 956, "width": 57, "height": 42}, "scaleRatio": {"x": 1.0, "y": 1.0}, "isMulti": false, "isMip": false, "isAlpha8": false, "hull": []}, {"name": "Fx\\SnowFootstepZag\\SnowFootstepZag0080", "topLeft": {"x": 11, "y": 18}, "originalSize": {"x": 80, "y": 80}, "rect": {"x": 2461, "y": 956, "width": 57, "height": 42}, "scaleRatio": {"x": 1.0, "y": 1.0}, "isMulti": false, "isMip": false, "isAlpha8": false, "hull": []}, {"name": "Fx\\SnowFootstepZag\\SnowFootstepZag0255", "topLeft": {"x": 12, "y": 24}, "originalSize": {"x": 80, "y": 80}, "rect": {"x": 1132, "y": 2561, "width": 57, "height": 40}, "scaleRatio": {"x": 1.0, "y": 1.0}, "isMulti": false, "isMip": false, "isAlpha8": false, "hull": []}, {"name": "Fx\\ElysiumButterflyCycleC\\ElysiumButterflyCycleC0133", "topLeft": {"x": 108, "y": 63}, "originalSize": {"x": 270, "y": 200}, "rect": {"x": 1189, "y": 2561, "width": 56, "height": 40}, "scaleRatio": {"x": 1.0, "y": 1.0}, "isMulti": false, "isMip": false, "isAlpha8": false, "hull": []}, {"name": "Fx\\SnowFootstepZag\\SnowFootstepZag0103", "topLeft": {"x": 12, "y": 22}, "originalSize": {"x": 80, "y": 80}, "rect": {"x": 2246, "y": 1466, "width": 56, "height": 40}, "scaleRatio": {"x": 1.0, "y": 1.0}, "isMulti": false, "isMip": false, "isAlpha8": false, "hull": []}, {"name": "Fx\\Grenade\\Grenade0073", "topLeft": {"x": 36, "y": 2}, "originalSize": {"x": 100, "y": 100}, "rect": {"x": 2497, "y": 0, "width": 28, "height": 52}, "scaleRatio": {"x": 1.0, "y": 1.0}, "isMulti": false, "isMip": false, "isAlpha8": false, "hull": []}, {"name": "Fx\\Grenade\\Grenade0074", "topLeft": {"x": 36, "y": 3}, "originalSize": {"x": 100, "y": 100}, "rect": {"x": 2497, "y": 52, "width": 28, "height": 52}, "scaleRatio": {"x": 1.0, "y": 1.0}, "isMulti": false, "isMip": false, "isAlpha8": false, "hull": []}, {"name": "Fx\\Grenade\\Grenade0037", "topLeft": {"x": 40, "y": 4}, "originalSize": {"x": 100, "y": 100}, "rect": {"x": 1081, "y": 2115, "width": 40, "height": 51}, "scaleRatio": {"x": 1.0, "y": 1.0}, "isMulti": false, "isMip": false, "isAlpha8": false, "hull": []}, {"name": "Fx\\ElysiumButterflyCycleD\\ElysiumButterflyCycleD0032", "topLeft": {"x": 19, "y": 33}, "originalSize": {"x": 200, "y": 200}, "rect": {"x": 2766, "y": 1129, "width": 50, "height": 35}, "scaleRatio": {"x": 1.0, "y": 1.0}, "isMulti": false, "isMip": false, "isAlpha8": false, "hull": []}, {"name": "Fx\\GrenadeRPG\\GrenadeRPG0006", "topLeft": {"x": 45, "y": 26}, "originalSize": {"x": 100, "y": 100}, "rect": {"x": 1759, "y": 916, "width": 50, "height": 35}, "scaleRatio": {"x": 1.0, "y": 1.0}, "isMulti": false, "isMip": false, "isAlpha8": false, "hull": []}, {"name": "Fx\\GrenadeRPG\\GrenadeRPG0028", "topLeft": {"x": 5, "y": 26}, "originalSize": {"x": 100, "y": 100}, "rect": {"x": 1264, "y": 1431, "width": 50, "height": 35}, "scaleRatio": {"x": 1.0, "y": 1.0}, "isMulti": false, "isMip": false, "isAlpha8": false, "hull": []}, {"name": "Fx\\SnowFootstepZag\\SnowFootstepZag0117", "topLeft": {"x": 14, "y": 24}, "originalSize": {"x": 80, "y": 80}, "rect": {"x": 1131, "y": 1205, "width": 49, "height": 35}, "scaleRatio": {"x": 1.0, "y": 1.0}, "isMulti": false, "isMip": false, "isAlpha8": false, "hull": []}, {"name": "Fx\\SnowFootstepZag\\SnowFootstepZag0133", "topLeft": {"x": 16, "y": 25}, "originalSize": {"x": 80, "y": 80}, "rect": {"x": 1180, "y": 1205, "width": 49, "height": 35}, "scaleRatio": {"x": 1.0, "y": 1.0}, "isMulti": false, "isMip": false, "isAlpha8": false, "hull": []}, {"name": "Fx\\SnowFootstepZag\\SnowFootstepZag0165", "topLeft": {"x": 16, "y": 23}, "originalSize": {"x": 80, "y": 80}, "rect": {"x": 2690, "y": 1386, "width": 49, "height": 37}, "scaleRatio": {"x": 1.0, "y": 1.0}, "isMulti": false, "isMip": false, "isAlpha8": false, "hull": []}, {"name": "Fx\\DarknessShard\\DarknessShard0037", "topLeft": {"x": 9, "y": 11}, "originalSize": {"x": 64, "y": 64}, "rect": {"x": 2739, "y": 1386, "width": 48, "height": 37}, "scaleRatio": {"x": 1.0, "y": 1.0}, "isMulti": false, "isMip": false, "isAlpha8": false, "hull": []}, {"name": "Fx\\MouseScurryD\\MouseScurryD0011", "topLeft": {"x": 254, "y": 156}, "originalSize": {"x": 400, "y": 300}, "rect": {"x": 452, "y": 2853, "width": 48, "height": 27}, "scaleRatio": {"x": 1.0, "y": 1.0}, "isMulti": false, "isMip": false, "isAlpha8": false, "hull": []}, {"name": "Fx\\MouseScurryA\\MouseScurryA0040", "topLeft": {"x": 132, "y": 58}, "originalSize": {"x": 400, "y": 300}, "rect": {"x": 500, "y": 2853, "width": 47, "height": 27}, "scaleRatio": {"x": 1.0, "y": 1.0}, "isMulti": false, "isMip": false, "isAlpha8": false, "hull": []}, {"name": "Fx\\MouseScurryA\\MouseScurryA0042", "topLeft": {"x": 135, "y": 58}, "originalSize": {"x": 400, "y": 300}, "rect": {"x": 547, "y": 2853, "width": 47, "height": 27}, "scaleRatio": {"x": 1.0, "y": 1.0}, "isMulti": false, "isMip": false, "isAlpha8": false, "hull": []}, {"name": "Fx\\MouseScurryA\\MouseScurryA0043", "topLeft": {"x": 136, "y": 57}, "originalSize": {"x": 400, "y": 300}, "rect": {"x": 594, "y": 2853, "width": 47, "height": 27}, "scaleRatio": {"x": 1.0, "y": 1.0}, "isMulti": false, "isMip": false, "isAlpha8": false, "hull": []}, {"name": "Fx\\MouseScurryA\\MouseScurryA0045", "topLeft": {"x": 139, "y": 56}, "originalSize": {"x": 400, "y": 300}, "rect": {"x": 641, "y": 2853, "width": 47, "height": 27}, "scaleRatio": {"x": 1.0, "y": 1.0}, "isMulti": false, "isMip": false, "isAlpha8": false, "hull": []}, {"name": "Fx\\MouseScurryD\\MouseScurryD0040", "topLeft": {"x": 276, "y": 248}, "originalSize": {"x": 400, "y": 300}, "rect": {"x": 688, "y": 2853, "width": 47, "height": 27}, "scaleRatio": {"x": 1.0, "y": 1.0}, "isMulti": false, "isMip": false, "isAlpha8": false, "hull": []}, {"name": "Fx\\Grenade\\Grenade0051", "topLeft": {"x": 42, "y": 27}, "originalSize": {"x": 100, "y": 100}, "rect": {"x": 1809, "y": 916, "width": 46, "height": 35}, "scaleRatio": {"x": 1.0, "y": 1.0}, "isMulti": false, "isMip": false, "isAlpha8": false, "hull": []}, {"name": "Fx\\SnowFootstepHades\\SnowFootstepHades0060", "topLeft": {"x": 27, "y": 27}, "originalSize": {"x": 100, "y": 100}, "rect": {"x": 1245, "y": 2561, "width": 45, "height": 40}, "scaleRatio": {"x": 1.0, "y": 1.0}, "isMulti": false, "isMip": false, "isAlpha8": false, "hull": []}, {"name": "Fx\\FootprintFoot\\FootprintFoot0017", "topLeft": {"x": 7, "y": 19}, "originalSize": {"x": 64, "y": 64}, "rect": {"x": 2252, "y": 2856, "width": 44, "height": 24}, "scaleRatio": {"x": 1.0, "y": 1.0}, "isMulti": false, "isMip": false, "isAlpha8": false, "hull": []}, {"name": "Fx\\Grenade\\Grenade0055", "topLeft": {"x": 41, "y": 37}, "originalSize": {"x": 100, "y": 100}, "rect": {"x": 735, "y": 2853, "width": 44, "height": 27}, "scaleRatio": {"x": 1.0, "y": 1.0}, "isMulti": false, "isMip": false, "isAlpha8": false, "hull": []}, {"name": "Fx\\Grenade\\Grenade0119", "topLeft": {"x": 15, "y": 37}, "originalSize": {"x": 100, "y": 100}, "rect": {"x": 779, "y": 2853, "width": 44, "height": 27}, "scaleRatio": {"x": 1.0, "y": 1.0}, "isMulti": false, "isMip": false, "isAlpha8": false, "hull": []}, {"name": "Fx\\MouseScurryA\\MouseScurryA0044", "topLeft": {"x": 138, "y": 57}, "originalSize": {"x": 400, "y": 300}, "rect": {"x": 823, "y": 2853, "width": 44, "height": 27}, "scaleRatio": {"x": 1.0, "y": 1.0}, "isMulti": false, "isMip": false, "isAlpha8": false, "hull": []}, {"name": "Fx\\MouseScurryD\\MouseScurryD0010", "topLeft": {"x": 257, "y": 158}, "originalSize": {"x": 400, "y": 300}, "rect": {"x": 2296, "y": 2856, "width": 44, "height": 24}, "scaleRatio": {"x": 1.0, "y": 1.0}, "isMulti": false, "isMip": false, "isAlpha8": false, "hull": []}, {"name": "Fx\\ElysiumButterflyCycleC\\ElysiumButterflyCycleC0008", "topLeft": {"x": 124, "y": 42}, "originalSize": {"x": 270, "y": 200}, "rect": {"x": 868, "y": 2605, "width": 37, "height": 43}, "scaleRatio": {"x": 1.0, "y": 1.0}, "isMulti": false, "isMip": false, "isAlpha8": false, "hull": []}, {"name": "Fx\\FootprintFoot\\FootprintFoot0016", "topLeft": {"x": 8, "y": 19}, "originalSize": {"x": 64, "y": 64}, "rect": {"x": 2340, "y": 2856, "width": 43, "height": 24}, "scaleRatio": {"x": 1.0, "y": 1.0}, "isMulti": false, "isMip": false, "isAlpha8": false, "hull": []}, {"name": "Fx\\MouseScurryA\\MouseScurryA0013", "topLeft": {"x": 197, "y": 108}, "originalSize": {"x": 400, "y": 300}, "rect": {"x": 867, "y": 2853, "width": 39, "height": 27}, "scaleRatio": {"x": 1.0, "y": 1.0}, "isMulti": false, "isMip": false, "isAlpha8": false, "hull": []}, {"name": "Fx\\SnowFootstepHades\\SnowFootstepHades0243", "topLeft": {"x": 30, "y": 33}, "originalSize": {"x": 100, "y": 100}, "rect": {"x": 2383, "y": 2856, "width": 39, "height": 24}, "scaleRatio": {"x": 1.0, "y": 1.0}, "isMulti": false, "isMip": false, "isAlpha8": false, "hull": []}, {"name": "Fx\\SnowFootstepHades\\SnowFootstepHades0171", "topLeft": {"x": 32, "y": 29}, "originalSize": {"x": 100, "y": 100}, "rect": {"x": 1314, "y": 1431, "width": 37, "height": 35}, "scaleRatio": {"x": 1.0, "y": 1.0}, "isMulti": false, "isMip": false, "isAlpha8": false, "hull": []}, {"name": "Fx\\SnowFootstepHades\\SnowFootstepHades0179", "topLeft": {"x": 34, "y": 30}, "originalSize": {"x": 100, "y": 100}, "rect": {"x": 1229, "y": 1205, "width": 34, "height": 35}, "scaleRatio": {"x": 1.0, "y": 1.0}, "isMulti": false, "isMip": false, "isAlpha8": false, "hull": []}, {"name": "Fx\\SnowFootstepZag\\SnowFootstepZag0163", "topLeft": {"x": 23, "y": 27}, "originalSize": {"x": 80, "y": 80}, "rect": {"x": 1967, "y": 2571, "width": 34, "height": 24}, "scaleRatio": {"x": 1.0, "y": 1.0}, "isMulti": false, "isMip": false, "isAlpha8": false, "hull": []}, {"name": "Fx\\Grenade\\Grenade0202", "topLeft": {"x": 36, "y": 37}, "originalSize": {"x": 100, "y": 100}, "rect": {"x": 2281, "y": 2775, "width": 28, "height": 33}, "scaleRatio": {"x": 1.0, "y": 1.0}, "isMulti": false, "isMip": false, "isAlpha8": false, "hull": []}], "isReference": true, "referencedTextureName": "bin\\Win\\Atlases\\ModsNikkelMHadesBiomesFxOriginal29"}