<?xml version="1.0" encoding="UTF-8"?>
<objects serializationModel="Studio.02.02.00">
	<object class="AudioFile" id="{4273df7a-f899-4205-9e28-fad7a78e2043}">
		<property name="assetPath">
			<value>AsphodelMusic3_DRUMS_REFACTOR.wav</value>
		</property>
		<property name="isStreaming">
			<value>true</value>
		</property>
		<property name="frequencyInKHz">
			<value>44.0999985</value>
		</property>
		<property name="channelCount">
			<value>2</value>
		</property>
		<property name="length">
			<value>307.40795918367348</value>
		</property>
		<relationship name="masterAssetFolder">
			<destination>{a3b346cc-7f6c-4b51-acb8-491971281eb5}</destination>
		</relationship>
	</object>
</objects>
