{"name": "bin\\Win\\Atlases\\ModsNikkelMHadesBiomesGUIOriginal3", "version": 4, "subAtlases": [{"name": "GUI\\Screens\\MainMenuUpdateImage_Charon", "topLeft": {"x": 0, "y": 0}, "originalSize": {"x": 1920, "y": 1080}, "rect": {"x": 0, "y": 0, "width": 1920, "height": 1080}, "scaleRatio": {"x": 1.0, "y": 1.0}, "isMulti": false, "isMip": false, "isAlpha8": false, "hull": []}, {"name": "GUI\\Screens\\MainMenuUpdateImage_DemeterCNY", "topLeft": {"x": 0, "y": 0}, "originalSize": {"x": 1920, "y": 1080}, "rect": {"x": 0, "y": 1080, "width": 1920, "height": 1080}, "scaleRatio": {"x": 1.0, "y": 1.0}, "isMulti": false, "isMip": false, "isAlpha8": false, "hull": []}, {"name": "GUI\\UnlockTextBG\\LocationTextBG0003", "topLeft": {"x": 0, "y": 0}, "originalSize": {"x": 1920, "y": 340}, "rect": {"x": 0, "y": 2160, "width": 1920, "height": 279}, "scaleRatio": {"x": 1.0, "y": 1.0}, "isMulti": false, "isMip": false, "isAlpha8": false, "hull": []}, {"name": "GUI\\UnlockTextBG\\LocationTextBG0004", "topLeft": {"x": 0, "y": 0}, "originalSize": {"x": 1920, "y": 340}, "rect": {"x": 0, "y": 2439, "width": 1920, "height": 278}, "scaleRatio": {"x": 1.0, "y": 1.0}, "isMulti": false, "isMip": false, "isAlpha8": false, "hull": []}, {"name": "GUI\\UnlockTextBG\\LocationTextBG0036", "topLeft": {"x": 4, "y": 88}, "originalSize": {"x": 1920, "y": 340}, "rect": {"x": 0, "y": 2717, "width": 1912, "height": 150}, "scaleRatio": {"x": 1.0, "y": 1.0}, "isMulti": false, "isMip": false, "isAlpha8": false, "hull": []}, {"name": "GUI\\Screens\\AwardMenu\\Legendary\\Achilles_01", "topLeft": {"x": 15, "y": 27}, "originalSize": {"x": 343, "y": 434}, "rect": {"x": 1920, "y": 2439, "width": 325, "height": 363}, "scaleRatio": {"x": 1.0, "y": 1.0}, "isMulti": false, "isMip": false, "isAlpha8": false, "hull": []}], "isReference": true, "referencedTextureName": "bin\\Win\\Atlases\\ModsNikkelMHadesBiomesGUIOriginal3"}